Workbook
Name AccountStatus: #REF!
Name BANKING_DATABASE_FINAL: #REF!
Name Beta: #REF!
Name Branch1: #REF!
Name Constant.No.Factor: [1]Score!$D$119
Name Country: OFFSET([2]Master!$B$3,1,0,COUNTA([2]Master!$B:$B)-1)
Name CrfFileName: [3]ws!$B$28
Name DataMonthName: [3]ws!$B$3
Name DataYear: [3]ws!$B$18
Name Excel_BuiltIn_Print_Area_10: #REF!
Name Excel_BuiltIn_Print_Area_10_1: NA()
Name Exclusion_Flag: OFFSET('[4]Score Generator'!$CK$8,0,0,COUNTA(INDIRECT("'Score Generator'!$A$5:$A"&ROWS('[4]Score Generator'!$A:$A))),1)
Name External_Credit_Rating: OFFSET('[5]Score Generator'!$BJ$8,0,0,COUNTA(INDIRECT("'Score Generator'!$A$5:$A"&ROWS('[5]Score Generator'!$A:$A))),1)
Name Issue_Priority: #REF!
Name Issue_Status: #REF!
Name Issue_Workstream: #REF!
Name NameThai: [3]ws!$H$5
Name PositionName: [3]ws!$H$6
Name PrintBy: [3]ws!$H$4
Name PrintDate: [3]ws!$H$3
Name Ref_No: OFFSET('[4]Score Generator'!$A$8,0,0,COUNTA(INDIRECT("'Score Generator'!$A$5:$A"&ROWS('[4]Score Generator'!$A:$A))),1)
Name ReqStatus: [6]Sheet1!$A$31:$A$33
Name Risk_Impact: #REF!
Name Risk_Probability: #REF!
Name Risk_Status: #REF!
Name Risk_Workstream: #REF!
Name Score_Gen_Value: OFFSET('[4]Score Generator'!$A$8,0,0,COUNTA(INDIRECT("'Score Generator'!$A$5:$A"&ROWS('[4]Score Generator'!$A:$A))),COUNTA('[4]Score Generator'!$A$5:$DF$5))
Name sfs: #REF!
Name Status: #REF!
Name u: #REF!
Name unrated: #REF!

Sheet Instructions
B2: Background and Problem Statement
B3: • This exercise is related to credit scoring or scorecard development. The loans portfolio in scope is SME portfolio of the Bank. • Due to fairly low defaulted cases (50 cases), the Credit Scorecard development would adopt the Hybrid approach (between Expert-based and Statistical analysis). • The weights of each feature and risk component of the scorecard are currently determined based on the Bank's credit experts judgement. • However, the Bank would like to employ data or quantiatative analysis to objectively support the determination of such weights.
B5: Input Data Provided:
B6: • This spreadsheet contains the input data for credit scorecard development.
B7: Notes for Input Data - Only eight generic features related to customers’ credit history and financial factors are provided for this exercise. - The Default Flag is provided (i.e. whether a customer has ever exceeded 90 days past due (DPD) within the next 24 months), where a value of 1 denotes default. - The sheet 'Data' contains data before applying binning or grouping. - The sheet 'Data_Bin' contains data after applying binning or grouping to numerical features. - Some numerical features contain specially assigned values (e.g., 99999999, 99999998) to indicate special cases or invalid calculations (such as when the denominator equals zero). - The sheet 'Scorecard' provides the assigned credit scores corresponding to each attribute..
B9: Instruction:
B10: • Please provide your answers in sheet 'Test'. The focus is to use data and quantitative analysis to justify and support your rationales or point of views. • You can use Python or MS Excel to perform the data and quantitative analysis. • You are required to prepare up to a total of 12 slides covering the following areas, the presentation slides you draft will be used as part of the interview evaluation process. • Please revert this file (and any necessary working files) and present your work in the session. You will have 20 minutes for the presentation.

Sheet Data
A1: Cus_ID | B1: Debt restructuring history | C1: Debt rescheduling history (reschedule) | D1: Worst credit bureau delinquency record in the past 2 years | E1: Net Fixed Asset | F1: Net Profit Margin (%) | G1: Sale Growth (%) | H1: Debt-to-Equity Ratio | I1: Debt Service Coverage Area | J1: Default Flag
A2: 1 | B2: No debt restructuring history | C2: No debt rescheduling history (payment term relief) | D2: Record found in credit bureau but no delinquency history | E2: 38169496 | F2: -113.26 | G2: -56.14 | H2: 99999998 | I2: -0.41179 | J2: 0
A3: 2 | B3: No debt restructuring history | C3: No debt rescheduling history (payment term relief) | D3: Record found in credit bureau but no delinquency history | E3: 16781677 | F3: -54.94 | G3: -6.99 | H3: 99999998 | I3: -0.31211 | J3: 0
A4: 3 | B4: No debt restructuring history | C4: No debt rescheduling history (payment term relief) | D4: Record found in credit bureau but no delinquency history | E4: 213151797 | F4: -84.12286 | G4: -46.76026 | H4: 0.53141 | I4: 0.0856 | J4: 0
A5: 4 | B5: No debt restructuring history | C5: No debt rescheduling history (payment term relief) | D5: Record found in credit bureau but no delinquency history | E5: 1181179164 | F5: -80.71586 | G5: -33.07817 | H5: 0.47271 | I5: 0.09958 | J5: 0
A6: 5 | B6: Restructured debt with regular payments for more than 12 months | C6: Rescheduled debt with regular payments for more than 12 months | D6: Record found in credit bureau but no delinquency history | E6: 3.7597975e+08 | F6: -285.6987 | G6: -84.03822 | H6: 99999998 | I6: 0.63897 | J6: 0
A7: 6 | B7: No debt restructuring history | C7: No debt rescheduling history (payment term relief) | D7: Record found in credit bureau but no delinquency history | E7: 72606642 | F7: -176.74375 | G7: -86.47437 | H7: 99999998 | I7: -1.09041 | J7: 0
A8: 7 | B8: Restructured debt with regular payments for 6-12 months | C8: Rescheduled debt with regular payments for 6-12 months | D8: Overdue more than 90 days within the past 1 year | E8: 3.0160438e+08 | F8: -92.85954 | G8: 55.35001 | H8: 0.7464 | I8: -0.81684 | J8: 0
A9: 8 | B9: No debt restructuring history | C9: Rescheduled debt with regular payments for 6-12 months | D9: Record found in credit bureau but no delinquency history | E9: 1.5420959e+09 | F9: 10.19 | G9: 30.86 | H9: 1.26157 | I9: 0.83338 | J9: 0
A10: 9 | B10: No debt restructuring history | C10: Rescheduled debt with regular payments for more than 12 months | D10: Record found in credit bureau but no delinquency history | E10: 27203707 | F10: -17.70526 | G10: -41.47401 | H10: 99999998 | I10: 0.23822 | J10: 0
A11: 10 | B11: No debt restructuring history | C11: No debt rescheduling history (payment term relief) | D11: Record found in credit bureau but no delinquency history | E11: 7086263.8 | F11: -92.61 | G11: -29.64 | H11: 1.11335 | I11: -0.02576 | J11: 0
A12: 11 | B12: No debt restructuring history | C12: No debt rescheduling history (payment term relief) | D12: Record found in credit bureau but no delinquency history | E12: 23169182 | F12: -205.41897 | G12: -69.58607 | H12: 99999998 | I12: -0.14431 | J12: 0
A13: 12 | B13: No debt restructuring history | C13: No debt rescheduling history (payment term relief) | D13: Record found in credit bureau but no delinquency history | E13: 1.3505688e+09 | F13: 13.064 | G13: -13.18579 | H13: 0.38582 | I13: 1.84288 | J13: 0
... A15: 14 | B15: No debt restructuring history | C15: Rescheduled debt with regular payments for less than 6 months | D15: Record found in credit bureau but no delinquency history | E15: 1.8146398e+08 | F15: -211.17703 | G15: -82.18576 | H15: -2.14765 | I15: -0.04452 | J15: 0
A16: 15 | B16: No debt restructuring history | C16: No debt rescheduling history (payment term relief) | D16: Record found in credit bureau but no delinquency history | E16: 1.8059602e+08 | F16: 1.97 | G16: -80.94 | H16: 0.51579 | J16: 0
A17: 16 | B17: No debt restructuring history | C17: Rescheduled debt with regular payments for less than 6 months | D17: Record found in credit bureau but no delinquency history | E17: 2.1792275e+08 | F17: -182.22162 | G17: -76.01723 | H17: 99999998 | I17: -0.28953 | J17: 0
A18: 17 | B18: No debt restructuring history | C18: Rescheduled debt with regular payments for more than 12 months | D18: Overdue 1-30 days within the past 1 year | E18: 83578129 | F18: -641.15591 | G18: -91.21621 | H18: 99999998 | I18: -0.29518 | J18: 0
A19: 18 | B19: No debt restructuring history | C19: No debt rescheduling history (payment term relief) | D19: Record found in credit bureau but no delinquency history | E19: 1.8076858e+08 | F19: -83.90369 | G19: 3.30007 | H19: 0.52191 | I19: -1.37526 | J19: 0
A20: 19 | B20: No debt restructuring history | C20: No debt rescheduling history (payment term relief) | D20: Record found in credit bureau but no delinquency history | E20: 1898769.7 | F20: -324.23 | G20: -55.21 | H20: 99999998 | I20: -0.00361 | J20: 0
A21: 20 | B21: No debt restructuring history | C21: No debt rescheduling history (payment term relief) | D21: Record found in credit bureau but no delinquency history | E21: 20436236 | F21: -127.93552 | G21: -77.07892 | H21: 99999998 | I21: -0.10384 | J21: 0
A22: 21 | B22: No debt restructuring history | C22: No debt rescheduling history (payment term relief) | D22: Record found in credit bureau but no delinquency history | E22: 28518995 | F22: -153.42 | G22: -41.02 | H22: 99999998 | I22: -0.17237 | J22: 0
A23: 22 | B23: No debt restructuring history | C23: No debt rescheduling history (payment term relief) | D23: Credit bureau check not performed (exempted) | E23: 9687738251 | F23: -128.02879 | G23: -66.37212 | H23: 2.43967 | I23: -0.37221 | J23: 0
A24: 23 | B24: No debt restructuring history | C24: › | D24: Record found in credit bureau but no delinquency history | E24: 3251922517 | F24: -3.31578 | G24: -9.62089 | H24: 0.75828 | I24: 0.94204 | J24: 0
A25: 24 | B25: No debt restructuring history | C25: No debt rescheduling history (payment term relief) | D25: Record found in credit bureau but no delinquency history | E25: 1.2945699e+08 | F25: -19.84688 | G25: -55.53527 | H25: 1.37861 | I25: 0.35044 | J25: 0
A26: 25 | B26: No debt restructuring history | C26: No debt rescheduling history (payment term relief) | D26: Credit bureau check not performed | E26: 68621430 | F26: -54.57 | G26: -30.81 | H26: 99999998 | I26: 1.94255 | J26: 0
A27: 26 | B27: No debt restructuring history | C27: No debt rescheduling history (payment term relief) | D27: Record found in credit bureau but no delinquency history | E27: 33257577 | F27: -36.72 | G27: 86.85 | H27: 2.00054 | I27: 2.35213 | J27: 0
A28: 27 | B28: No debt restructuring history | C28: No debt rescheduling history (payment term relief) | D28: Record found in credit bureau but no delinquency history | E28: 2.5183254e+08 | F28: -274.57551 | G28: -86.51197 | H28: 99999998 | I28: -0.56665 | J28: 0
... A36: 35 | B36: Restructured debt with regular payments for 6-12 months | C36: Rescheduled debt with regular payments for 6-12 months | D36: Overdue more than 90 days within the past 1 year | E36: 60588794 | F36: -347.81089 | G36: -0.26914 | H36: 99999998 | I36: -0.98191 | J36: 0
A37: 36 | B37: Restructured debt with regular payments for less than 6 months | C37: Rescheduled debt with regular payments for 6-12 months | D37: Overdue more than 90 days within the past 1 year | E37: 56114.95 | F37: 42.12968 | G37: -29.20168 | H37: 0.01669 | J37: 1
A38: 37 | B38: No debt restructuring history | C38: No debt rescheduling history (payment term relief) | D38: Record found in credit bureau but no delinquency history | E38: 1.9535134e+08 | F38: -10.51651 | G38: -3.47424 | H38: -2.76748 | I38: 0.66035 | J38: 0
A39: 38 | B39: No debt restructuring history | C39: No debt rescheduling history (payment term relief) | D39: Record found in credit bureau but no delinquency history | E39: 2.348659e+08 | F39: -2.86 | G39: -5.36 | H39: -3.61112 | I39: 0.79104 | J39: 0
A40: 39 | B40: No debt restructuring history | C40: No debt rescheduling history (payment term relief) | D40: Record found in credit bureau but no delinquency history | E40: 69932010 | F40: 6.98248 | G40: -70.25848 | H40: 2.11822 | I40: 1.19782 | J40: 0
A41: 40 | B41: No debt restructuring history | C41: No debt rescheduling history (payment term relief) | D41: Credit bureau check not performed (exempted) | E41: 2532176365 | F41: -27.21663 | G41: -37.64652 | H41: 15.21586 | I41: -7.93745 | J41: 0
A42: 41 | B42: Restructured debt with regular payments for less than 6 months | C42: Rescheduled debt with regular payments for 6-12 months | D42: Overdue more than 90 days within the past 1 year | E42: 56114.95 | F42: 42.12968 | G42: -29.20168 | H42: 99999999 | J42: 1
A43: 42 | B43: No debt restructuring history | C43: No debt rescheduling history (payment term relief) | D43: Record found in credit bureau but no delinquency history | E43: 75005392 | F43: -24.65699 | G43: -10.73973 | H43: 0.63251 | I43: 2.35407 | J43: 0
A44: 43 | B44: Restructured debt with regular payments for more than 12 months | C44: Rescheduled debt with regular payments for more than 12 months | D44: Record found in credit bureau but no delinquency history | E44: 4.0310022e+08 | F44: 33.73 | G44: -4.76 | H44: 99999998 | I44: 1.79804 | J44: 0
A45: 44 | B45: No debt restructuring history | C45: No debt rescheduling history (payment term relief) | D45: Record found in credit bureau but no delinquency history | E45: 53753485 | F45: 1.08 | G45: -4.13 | H45: 0.54547 | I45: 0.79049 | J45: 0
A46: 45 | B46: No debt restructuring history | C46: Rescheduled debt with regular payments for more than 12 months | D46: Record found in credit bureau but no delinquency history | E46: 23803228 | F46: -0.65055 | G46: -3.12187 | H46: 99999999 | I46: 0.62879 | J46: 0
A47: 46 | B47: No debt restructuring history | C47: Rescheduled debt with regular payments for more than 12 months | D47: Record found in credit bureau but no delinquency history | E47: 144304127 | F47: 1.59016 | G47: -11.11203 | H47: -8.58703 | I47: 0.80596 | J47: 0
A48: 47 | B48: No debt restructuring history | C48: Rescheduled debt with regular payments for 6-12 months | D48: Overdue 61–90 days within the past 1 year | E48: 1.6052255e+09 | F48: -73.62 | G48: 18.3 | H48: 1.34697 | I48: 0.18769 | J48: 0
A49: 48 | B49: Restructured debt with regular payments for 6-12 months | C49: Rescheduled debt with regular payments for 6-12 months | D49: Overdue more than 90 days within the past 1 year | E49: 60588794 | F49: -347.81089 | G49: -0.26914 | H49: 99999998 | I49: -0.98191 | J49: 0
A50: 49 | B50: No debt restructuring history | C50: No debt rescheduling history (payment term relief) | D50: Record found in credit bureau but no delinquency history | E50: 29732983 | F50: -139.75607 | G50: -48.27232 | H50: 99999998 | I50: -0.43837 | J50: 0
A51: 50 | B51: No debt restructuring history | C51: No debt rescheduling history (payment term relief) | D51: Credit bureau check not performed (exempted) | E51: 7954708190 | F51: 11.49324 | G51: 4.20544 | H51: 0.79309 | I51: 0.99038 | J51: 0
A52: 51 | B52: No debt restructuring history | C52: No debt rescheduling history (payment term relief) | D52: Record found in credit bureau but no delinquency history | E52: 1.3335228e+08 | F52: 1.49638 | G52: -17.29882 | H52: 0.30558 | I52: 0.80124 | J52: 0
A53: 52 | B53: No debt restructuring history | C53: No debt rescheduling history (payment term relief) | D53: Record found in credit bureau but no delinquency history | E53: 7546126.5 | F53: -112.38 | G53: -14.66 | H53: 99999999 | I53: -0.26376 | J53: 0
A54: 53 | B54: Restructured debt with regular payments for 6-12 months | C54: Rescheduled debt with regular payments for more than 12 months | D54: Overdue 1-30 days within the past 1 year | E54: 47001625 | F54: -5.37876 | G54: -9.86952 | H54: 0.9865 | I54: 4.95946 | J54: 0
... A74: 73 | B74: No debt restructuring history | C74: No debt rescheduling history (payment term relief) | D74: Record found in credit bureau but no delinquency history | E74: 80533524 | F74: 23.18436 | G74: 15.75893 | H74: 99999998 | I74: 4.52407 | J74: 0
A75: 74 | B75: No debt restructuring history | C75: No debt rescheduling history (payment term relief) | D75: Record found in credit bureau but no delinquency history | E75: 40037259 | F75: -36.52383 | G75: 502.64095 | H75: 99999998 | J75: 0
A76: 75 | B76: Restructured debt with regular payments for less than 6 months | C76: Rescheduled debt with regular payments for less than 6 months | D76: Overdue more than 90 days within the past 1 year | E76: 3.0020547e+08 | F76: -219.84972 | G76: 10.21502 | H76: 1.3062 | I76: -1.3257 | J76: 0
A77: 76 | B77: No debt restructuring history | C77: No debt rescheduling history (payment term relief) | D77: Overdue 61–90 days within the past 1 year | E77: 1.0314159e+08 | F77: -28.89894 | G77: 78.06859 | H77: 99999998 | I77: -0.12231 | J77: 1
A78: 77 | B78: No debt restructuring history | C78: No debt rescheduling history (payment term relief) | D78: Credit bureau check not performed (exempted) | E78: 1322323528 | F78: 14.09322 | G78: 8.23 | H78: 1.38302 | I78: 65.74187 | J78: 0
A79: 78 | B79: No debt restructuring history | C79: No debt rescheduling history (payment term relief) | D79: Record found in credit bureau but no delinquency history | E79: 2195222.1 | F79: -188.51998 | G79: -0.97566 | H79: 2.51328 | I79: -0.01895 | J79: 0
A80: 79 | B80: No debt restructuring history | C80: No debt rescheduling history (payment term relief) | D80: Record found in credit bureau but no delinquency history | E80: 80975833 | F80: -20.5265 | G80: -12.94674 | H80: 0.83967 | I80: 2.15814 | J80: 0
A81: 80 | B81: Restructured debt with regular payments for less than 6 months | C81: Rescheduled debt with regular payments for less than 6 months | D81: Overdue more than 90 days within the past 1 year | E81: 3.0020547e+08 | F81: -219.84972 | G81: 10.21502 | H81: 1.3062 | I81: -1.3257 | J81: 0
A82: 81 | B82: No debt restructuring history | C82: Rescheduled debt with regular payments for more than 12 months | D82: Record found in credit bureau but no delinquency history | E82: 25154728 | F82: 4.75365 | G82: 1.05585 | H82: 99999998 | I82: 0.90492 | J82: 0
A83: 82 | B83: No debt restructuring history | C83: Rescheduled debt with regular payments for less than 6 months | D83: Record found in credit bureau but no delinquency history | E83: 11539796 | F83: -881.10465 | G83: -9.95363 | H83: 99999998 | I83: -0.47263 | J83: 0
A84: 83 | B84: No debt restructuring history | C84: No debt rescheduling history (payment term relief) | D84: No record found in credit bureau | J84: 0
A85: 84 | B85: No debt restructuring history | C85: No debt rescheduling history (payment term relief) | D85: Record found in credit bureau but no delinquency history | E85: 346296039 | F85: 2.71629 | G85: 6.18657 | H85: 0.32974 | I85: 509.50398 | J85: 0
A86: 85 | B86: Restructured debt with regular payments for more than 12 months | C86: Rescheduled debt with regular payments for 6-12 months | D86: Credit bureau check not performed | E86: 573026.24 | F86: -90.67006 | G86: 2.47045 | H86: 2.91684 | I86: 0.16251 | J86: 1
A87: 86 | B87: Restructured debt with regular payments for 6-12 months | C87: Rescheduled debt with regular payments for 6-12 months | D87: Record found in credit bureau but no delinquency history | E87: 71728793 | F87: -262.74483 | G87: -5.571 | H87: 99999998 | I87: 0.16136 | J87: 1
A88: 87 | B88: No debt restructuring history | C88: No debt rescheduling history (payment term relief) | D88: Record found in credit bureau but no delinquency history | E88: 53753485 | F88: 1.07698 | G88: -4.13309 | H88: 1.29929 | I88: 0.79049 | J88: 0
A89: 88 | B89: No debt restructuring history | C89: No debt rescheduling history (payment term relief) | D89: Record found in credit bureau but no delinquency history | E89: 30834601 | F89: -9.72398 | G89: 9.29566 | H89: 99999998 | I89: 1.20857 | J89: 0
A90: 89 | B90: No debt restructuring history | C90: No debt rescheduling history (payment term relief) | D90: Record found in credit bureau but no delinquency history | E90: 2.0958817e+08 | F90: -3.41 | G90: 8.41 | H90: -4.35856 | I90: 0.88216 | J90: 0
A91: 90 | B91: Restructured debt with regular payments for 6-12 months | C91: Rescheduled debt with regular payments for more than 12 months | D91: Overdue 1-30 days within the past 1 year | E91: 57209203 | F91: 0.46 | G91: -2.77 | H91: 1.00427 | I91: 3.62942 | J91: 0
A92: 91 | B92: No debt restructuring history | C92: No debt rescheduling history (payment term relief) | D92: Record found in credit bureau but no delinquency history | E92: 2.7331225e+08 | F92: 30.71604 | G92: 13.72824 | H92: 99999998 | I92: 3.51193 | J92: 0
A93: 92 | B93: No debt restructuring history | C93: No debt rescheduling history (payment term relief) | D93: Record found in credit bureau but no delinquency history | E93: 2082233176 | F93: 6.21 | G93: 40.07 | H93: 0.46031 | I93: 1.39114 | J93: 0
A94: 93 | B94: No debt restructuring history | C94: No debt rescheduling history (payment term relief) | D94: Credit bureau check not performed (exempted) | E94: 7414121962 | F94: 11.75 | G94: 0.13 | H94: 0.80181 | I94: 0.82951 | J94: 0
A95: 94 | B95: Restructured debt with regular payments for less than 6 months | C95: Rescheduled debt with regular payments for 6-12 months | D95: Overdue 1-30 days within the past 1 year | E95: 15602.3 | F95: 33.53685 | G95: 149.97246 | H95: 0.36847 | J95: 1
A96: 95 | B96: Restructured debt with regular payments for 6-12 months | C96: Rescheduled debt with regular payments for 6-12 months | D96: Overdue 1-30 days within the past 1 year | E96: 62839824 | F96: -153.20875 | G96: -57.95033 | H96: 99999998 | J96: 1
A97: 96 | B97: No debt restructuring history | C97: No debt rescheduling history (payment term relief) | D97: Record found in credit bureau but no delinquency history | E97: 21602977 | F97: 7.32756 | G97: 4.79452 | H97: 99999998 | I97: 0.69601 | J97: 0
A98: 97 | B98: No debt restructuring history | C98: No debt rescheduling history (payment term relief) | D98: Record found in credit bureau but no delinquency history | E98: 1.5157307e+09 | F98: 8.15623 | G98: 4.865 | H98: 0.26055 | I98: 1.0043 | J98: 0
A99: 98 | B99: No debt restructuring history | C99: No debt rescheduling history (payment term relief) | D99: Record found in credit bureau but no delinquency history | E99: 6.3149032e+08 | F99: -11.87489 | G99: 3.77912 | H99: 99999998 | I99: 0.29376 | J99: 0
A100: 99 | B100: No debt restructuring history | C100: No debt rescheduling history (payment term relief) | D100: Record found in credit bureau but no delinquency history | E100: 3.0786818e+08 | F100: 4.06507 | G100: 12.55828 | H100: 12.33619 | I100: 2.66825 | J100: 0
A101: 100 | B101: No debt restructuring history | C101: Rescheduled debt with regular payments for more than 12 months | D101: Record found in credit bureau but no delinquency history | E101: 1.3501314e+08 | F101: -13.9959 | G101: -14.56924 | H101: 99999998 | I101: 0.52941 | J101: 0
A102: 101 | B102: No debt restructuring history | C102: No debt rescheduling history (payment term relief) | D102: Overdue 1-30 days within the past 1 year | E102: 12345186 | F102: -76.21984 | G102: -24.91324 | H102: 99999998 | I102: -0.7029 | J102: 0
A103: 102 | B103: No debt restructuring history | C103: No debt rescheduling history (payment term relief) | D103: Record found in credit bureau but no delinquency history | E103: 77436815 | F103: 86.19543 | G103: 109.49247 | H103: 2.75808 | I103: 2.39569 | J103: 0
A104: 103 | B104: No debt restructuring history | C104: Rescheduled debt with regular payments for more than 12 months | D104: Record found in credit bureau but no delinquency history | E104: 151592437 | F104: 13.867 | G104: -2.07304 | H104: -5.81457 | I104: 1.20835 | J104: 0
A105: 104 | B105: No debt restructuring history | C105: No debt rescheduling history (payment term relief) | D105: Overdue 1-30 days within the past 1 year | E105: 3.6026708e+08 | F105: -20.66421 | G105: 634.02143 | H105: 8.74378 | I105: 0.96194 | J105: 0
A106: 105 | B106: Restructured debt with regular payments for more than 12 months | C106: No debt rescheduling history (payment term relief) | D106: Record found in credit bureau but no delinquency history | E106: 2.392527e+08 | F106: -17.21 | G106: 8.24 | H106: 0.59016 | I106: 0.54491 | J106: 0
A107: 106 | B107: No debt restructuring history | C107: No debt rescheduling history (payment term relief) | D107: Record found in credit bureau but no delinquency history | E107: 86372106 | F107: 1.69662 | G107: 43.24228 | H107: 18.05317 | J107: 0
A108: 107 | B108: No debt restructuring history | C108: Rescheduled debt with regular payments for more than 12 months | D108: Record found in credit bureau but no delinquency history | E108: 4.5652066e+08 | F108: -24.38563 | G108: 1.47648 | H108: 1.22595 | I108: 0.66312 | J108: 0
A109: 108 | B109: No debt restructuring history | C109: No debt rescheduling history (payment term relief) | D109: Overdue 1-30 days within the past 1 year | E109: 1.2740597e+08 | F109: 99999999 | G109: 99999999 | H109: 1.34211 | I109: 0.73829 | J109: 0
A110: 109 | B110: No debt restructuring history | C110: No debt rescheduling history (payment term relief) | D110: Record found in credit bureau but no delinquency history | E110: 287510865 | F110: 7.86657 | G110: 8.89349 | H110: 0.5906 | I110: 1.1353 | J110: 0
A111: 110 | B111: No debt restructuring history | C111: No debt rescheduling history (payment term relief) | D111: Record found in credit bureau but no delinquency history | E111: 1294745219 | F111: -51.73126 | G111: 138.38414 | H111: 0.59127 | I111: 0.1406 | J111: 0
A112: 111 | B112: No debt restructuring history | C112: No debt rescheduling history (payment term relief) | D112: Record found in credit bureau but no delinquency history | E112: 84467490 | F112: 20.30459 | G112: 15.98122 | H112: 99999998 | I112: 3.26207 | J112: 0
A113: 112 | B113: No debt restructuring history | C113: No debt rescheduling history (payment term relief) | D113: Record found in credit bureau but no delinquency history | E113: 87157529 | F113: -12.74476 | G113: 55.70969 | H113: 1.06102 | I113: 2.20009 | J113: 0
A114: 113 | B114: Restructured debt with regular payments for more than 12 months | C114: Rescheduled debt with regular payments for more than 12 months | D114: Overdue 1-30 days within the past 1 year | E114: 44574885 | F114: -172.8 | G114: -13.66 | H114: 99999998 | I114: 0.37483 | J114: 0
A115: 114 | B115: No debt restructuring history | C115: No debt rescheduling history (payment term relief) | D115: Record found in credit bureau but no delinquency history | E115: 12843836 | F115: 15.78 | G115: 10.95 | H115: 99999998 | I115: 0.91261 | J115: 0
A116: 115 | B116: No debt restructuring history | C116: No debt rescheduling history (payment term relief) | D116: Overdue 1-30 days within the past 1 year | E116: 31990198 | F116: -62.4076 | G116: -13.6973 | H116: 99999998 | I116: -0.36885 | J116: 0
A117: 116 | B117: Restructured debt with regular payments for more than 12 months | C117: No debt rescheduling history (payment term relief) | D117: Record found in credit bureau but no delinquency history | E117: 1.0098357e+08 | F117: 0.69796 | G117: 4.94837 | H117: 1.4654 | I117: 1.13526 | J117: 0
A118: 117 | B118: No debt restructuring history | C118: No debt rescheduling history (payment term relief) | D118: Overdue 61–90 days within the past 1 year | E118: 782082130 | F118: -8.07 | G118: -2.73 | H118: 1.1314 | I118: 0.76015 | J118: 1
A119: 118 | B119: No debt restructuring history | C119: No debt rescheduling history (payment term relief) | D119: Overdue 1-30 days within the past 1 year | E119: 1.4924129e+08 | F119: -30.95159 | G119: 24.29734 | H119: 99999998 | I119: 0.32168 | J119: 0
... A127: 126 | B127: No debt restructuring history | C127: No debt rescheduling history (payment term relief) | D127: Overdue more than 90 days within the past 1 year | E127: 93678495 | F127: 6.76 | G127: -9.87 | H127: 1.90019 | I127: 13.49413 | J127: 0
A128: 127 | B128: Restructured debt with regular payments for 6-12 months | C128: Rescheduled debt with regular payments for less than 6 months | D128: Overdue more than 90 days more than 1 year ago | E128: 64988944 | F128: 3.88855 | G128: 180.86446 | H128: 21.49879 | J128: 1
A129: 128 | B129: Restructured debt with regular payments for less than 6 months | C129: Rescheduled debt with regular payments for less than 6 months | D129: Overdue more than 90 days within the past 1 year | E129: 2.9417041e+08 | F129: -275.80674 | G129: -45.79681 | H129: 0.99613 | I129: -2.79504 | J129: 0
A130: 129 | B130: No debt restructuring history | C130: No debt rescheduling history (payment term relief) | D130: Record found in credit bureau but no delinquency history | E130: 161643.83 | F130: -1046.19 | G130: 99999999 | H130: 4.32132 | I130: -0.86748 | J130: 0
A131: 130 | B131: No debt restructuring history | C131: No debt rescheduling history (payment term relief) | D131: Record found in credit bureau but no delinquency history | E131: 1.5033421e+09 | F131: 6.59393 | G131: -9.09634 | H131: 0.3766 | I131: 1.75171 | J131: 0
A132: 131 | B132: No debt restructuring history | C132: No debt rescheduling history (payment term relief) | D132: Record found in credit bureau but no delinquency history | E132: 2.7675697e+08 | F132: -3.70314 | G132: 0.04162 | H132: 14.41545 | I132: 0.81992 | J132: 0
A133: 132 | B133: No debt restructuring history | C133: No debt rescheduling history (payment term relief) | D133: Record found in credit bureau but no delinquency history | E133: 2.3791901e+08 | F133: -17.78538 | G133: 2402.6549 | H133: -3.78467 | I133: 1.09794 | J133: 0
A134: 133 | B134: No debt restructuring history | C134: No debt rescheduling history (payment term relief) | D134: Credit bureau check not performed (exempted) | E134: 6710071750 | F134: -25.16 | G134: 4.73 | H134: 0.803 | I134: -0.05253 | J134: 0
...

Sheet Data_Bin
A1: Cus_ID | B1: Debt restructuring history | C1: Debt rescheduling history (reschedule) | D1: Worst credit bureau delinquency record in the past 2 years | E1: Net Fixed Asset | F1: Net Profit Margin (%) | G1: Sale Growth (%) | H1: Debt-to-Equity Ratio | I1: Debt Service Coverage Area | J1: Default Flag
A2: 1 | B2: No debt restructuring history | C2: No debt rescheduling history (payment term relief) | D2: Record found in credit bureau but no delinquency history | E2: (0, 50000000) | F2: <=0 | G2: <=0 | H2: 99999998 | I2: <=0 | J2: 0
A3: 2 | B3: No debt restructuring history | C3: No debt rescheduling history (payment term relief) | D3: Record found in credit bureau but no delinquency history | E3: (0, 50000000) | F3: <=0 | G3: <=0 | H3: 99999998 | I3: <=0 | J3: 0
A4: 3 | B4: No debt restructuring history | C4: No debt rescheduling history (payment term relief) | D4: Record found in credit bureau but no delinquency history | E4: (150000000, 250000000) | F4: <=0 | G4: <=0 | H4: (0.5, 1) | I4: (0, 0.25) | J4: 0
A5: 4 | B5: No debt restructuring history | C5: No debt rescheduling history (payment term relief) | D5: Record found in credit bureau but no delinquency history | E5: >250000000 | F5: <=0 | G5: <=0 | H5: (0, 0.5) | I5: (0, 0.25) | J5: 0
A6: 5 | B6: Restructured debt with regular payments for more than 12 months | C6: Rescheduled debt with regular payments for more than 12 months | D6: Record found in credit bureau but no delinquency history | E6: >250000000 | F6: <=0 | G6: <=0 | H6: 99999998 | I6: (0.5, 0.75) | J6: 0
A7: 6 | B7: No debt restructuring history | C7: No debt rescheduling history (payment term relief) | D7: Record found in credit bureau but no delinquency history | E7: (50000000, 100000000) | F7: <=0 | G7: <=0 | H7: 99999998 | I7: <=0 | J7: 0
A8: 7 | B8: Restructured debt with regular payments for 6-12 months | C8: Rescheduled debt with regular payments for 6-12 months | D8: Overdue more than 90 days within the past 1 year | E8: >250000000 | F8: <=0 | G8: >30 | H8: (0.5, 1) | I8: <=0 | J8: 0
A9: 8 | B9: No debt restructuring history | C9: Rescheduled debt with regular payments for 6-12 months | D9: Record found in credit bureau but no delinquency history | E9: >250000000 | F9: (7.5, 15) | G9: >30 | H9: (1, 1.5) | I9: (0.75, 1) | J9: 0
A10: 9 | B10: No debt restructuring history | C10: Rescheduled debt with regular payments for more than 12 months | D10: Record found in credit bureau but no delinquency history | E10: (0, 50000000) | F10: <=0 | G10: <=0 | H10: 99999998 | I10: (0, 0.25) | J10: 0
A11: 10 | B11: No debt restructuring history | C11: No debt rescheduling history (payment term relief) | D11: Record found in credit bureau but no delinquency history | E11: (0, 50000000) | F11: <=0 | G11: <=0 | H11: (1, 1.5) | I11: <=0 | J11: 0
A12: 11 | B12: No debt restructuring history | C12: No debt rescheduling history (payment term relief) | D12: Record found in credit bureau but no delinquency history | E12: (0, 50000000) | F12: <=0 | G12: <=0 | H12: 99999998 | I12: <=0 | J12: 0
A13: 12 | B13: No debt restructuring history | C13: No debt rescheduling history (payment term relief) | D13: Record found in credit bureau but no delinquency history | E13: >250000000 | F13: (7.5, 15) | G13: <=0 | H13: (0, 0.5) | I13: (1.2, 2) | J13: 0
A14: 13 | B14: No debt restructuring history | C14: Rescheduled debt with regular payments for less than 6 months | D14: Record found in credit bureau but no delinquency history | E14: (50000000, 100000000) | F14: <=0 | G14: <=0 | H14: (0.5, 1) | I14: (0.25, 0.5) | J14: 0
A15: 14 | B15: No debt restructuring history | C15: Rescheduled debt with regular payments for less than 6 months | D15: Record found in credit bureau but no delinquency history | E15: (150000000, 250000000) | F15: <=0 | G15: <=0 | H15: <=0 | I15: <=0 | J15: 0
A16: 15 | B16: No debt restructuring history | C16: No debt rescheduling history (payment term relief) | D16: Record found in credit bureau but no delinquency history | E16: (150000000, 250000000) | F16: (0, 2.5) | G16: <=0 | H16: (0.5, 1) | J16: 0
A17: 16 | B17: No debt restructuring history | C17: Rescheduled debt with regular payments for less than 6 months | D17: Record found in credit bureau but no delinquency history | E17: (150000000, 250000000) | F17: <=0 | G17: <=0 | H17: 99999998 | I17: <=0 | J17: 0
A18: 17 | B18: No debt restructuring history | C18: Rescheduled debt with regular payments for more than 12 months | D18: Overdue 1-30 days within the past 1 year | E18: (50000000, 100000000) | F18: <=0 | G18: <=0 | H18: 99999998 | I18: <=0 | J18: 0
A19: 18 | B19: No debt restructuring history | C19: No debt rescheduling history (payment term relief) | D19: Record found in credit bureau but no delinquency history | E19: (150000000, 250000000) | F19: <=0 | G19: (0, 5) | H19: (0.5, 1) | I19: <=0 | J19: 0
A20: 19 | B20: No debt restructuring history | C20: No debt rescheduling history (payment term relief) | D20: Record found in credit bureau but no delinquency history | E20: (0, 50000000) | F20: <=0 | G20: <=0 | H20: 99999998 | I20: <=0 | J20: 0
A21: 20 | B21: No debt restructuring history | C21: No debt rescheduling history (payment term relief) | D21: Record found in credit bureau but no delinquency history | E21: (0, 50000000) | F21: <=0 | G21: <=0 | H21: 99999998 | I21: <=0 | J21: 0
A22: 21 | B22: No debt restructuring history | C22: No debt rescheduling history (payment term relief) | D22: Record found in credit bureau but no delinquency history | E22: (0, 50000000) | F22: <=0 | G22: <=0 | H22: 99999998 | I22: <=0 | J22: 0
A23: 22 | B23: No debt restructuring history | C23: No debt rescheduling history (payment term relief) | D23: Credit bureau check not performed (exempted) | E23: >250000000 | F23: <=0 | G23: <=0 | H23: (1.5, 3) | I23: <=0 | J23: 0
A24: 23 | B24: No debt restructuring history | C24: No debt rescheduling history (payment term relief) | D24: Record found in credit bureau but no delinquency history | E24: >250000000 | F24: <=0 | G24: <=0 | H24: (0.5, 1) | I24: (0.75, 1) | J24: 0
A25: 24 | B25: No debt restructuring history | C25: No debt rescheduling history (payment term relief) | D25: Record found in credit bureau but no delinquency history | E25: (100000000, 150000000) | F25: <=0 | G25: <=0 | H25: (1, 1.5) | I25: (0.25, 0.5) | J25: 0
A26: 25 | B26: No debt restructuring history | C26: No debt rescheduling history (payment term relief) | D26: Credit bureau check not performed | E26: (50000000, 100000000) | F26: <=0 | G26: <=0 | H26: 99999998 | I26: (1.2, 2) | J26: 0
A27: 26 | B27: No debt restructuring history | C27: No debt rescheduling history (payment term relief) | D27: Record found in credit bureau but no delinquency history | E27: (0, 50000000) | F27: <=0 | G27: >30 | H27: (1.5, 3) | I27: >2 | J27: 0
A28: 27 | B28: No debt restructuring history | C28: No debt rescheduling history (payment term relief) | D28: Record found in credit bureau but no delinquency history | E28: >250000000 | F28: <=0 | G28: <=0 | H28: 99999998 | I28: <=0 | J28: 0
A29: 28 | B29: No debt restructuring history | C29: No debt rescheduling history (payment term relief) | D29: Overdue more than 90 days within the past 1 year | E29: (50000000, 100000000) | F29: 99999999 | G29: <=0 | H29: (1.5, 3) | I29: <=0 | J29: 0
A30: 29 | B30: No debt restructuring history | C30: No debt rescheduling history (payment term relief) | D30: Record found in credit bureau but no delinquency history | E30: >250000000 | F30: <=0 | G30: <=0 | H30: (0, 0.5) | I30: (0.5, 0.75) | J30: 0
A31: 30 | B31: No debt restructuring history | C31: Rescheduled debt with regular payments for less than 6 months | D31: Record found in credit bureau but no delinquency history | E31: (100000000, 150000000) | F31: 99999999 | G31: 99999999 | H31: (1, 1.5) | I31: <=0 | J31: 0
A32: 31 | B32: No debt restructuring history | C32: Rescheduled debt with regular payments for less than 6 months | D32: Overdue 1-30 days within the past 1 year | E32: >250000000 | F32: >15 | G32: <=0 | H32: (1.5, 3) | I32: (1.2, 2) | J32: 0
A33: 32 | B33: No debt restructuring history | C33: No debt rescheduling history (payment term relief) | D33: Credit bureau check not performed (exempted) | E33: >250000000 | F33: <=0 | G33: <=0 | H33: (1.5, 3) | I33: <=0 | J33: 0
A34: 33 | B34: No debt restructuring history | C34: Rescheduled debt with regular payments for more than 12 months | D34: Record found in credit bureau but no delinquency history | E34: (100000000, 150000000) | F34: (0, 2.5) | G34: <=0 | H34: <=0 | I34: (0.75, 1) | J34: 0
A35: 34 | B35: No debt restructuring history | C35: No debt rescheduling history (payment term relief) | D35: Overdue 31–60 days within the past 1 year | E35: (50000000, 100000000) | F35: (2.5, 7.5) | G35: <=0 | H35: (1.5, 3) | I35: (1, 1.2) | J35: 0
A36: 35 | B36: Restructured debt with regular payments for 6-12 months | C36: Rescheduled debt with regular payments for 6-12 months | D36: Overdue more than 90 days within the past 1 year | E36: (50000000, 100000000) | F36: <=0 | G36: <=0 | H36: 99999998 | I36: <=0 | J36: 0
A37: 36 | B37: Restructured debt with regular payments for less than 6 months | C37: Rescheduled debt with regular payments for 6-12 months | D37: Overdue more than 90 days within the past 1 year | E37: (0, 50000000) | F37: >15 | G37: <=0 | H37: (0, 0.5) | J37: 1
A38: 37 | B38: No debt restructuring history | C38: No debt rescheduling history (payment term relief) | D38: Record found in credit bureau but no delinquency history | E38: (150000000, 250000000) | F38: <=0 | G38: <=0 | H38: <=0 | I38: (0.5, 0.75) | J38: 0
A39: 38 | B39: No debt restructuring history | C39: No debt rescheduling history (payment term relief) | D39: Record found in credit bureau but no delinquency history | E39: (150000000, 250000000) | F39: <=0 | G39: <=0 | H39: <=0 | I39: (0.75, 1) | J39: 0
A40: 39 | B40: No debt restructuring history | C40: No debt rescheduling history (payment term relief) | D40: Record found in credit bureau but no delinquency history | E40: (50000000, 100000000) | F40: (2.5, 7.5) | G40: <=0 | H40: (1.5, 3) | I40: (1, 1.2) | J40: 0
A41: 40 | B41: No debt restructuring history | C41: No debt rescheduling history (payment term relief) | D41: Credit bureau check not performed (exempted) | E41: >250000000 | F41: <=0 | G41: <=0 | H41: >5 | I41: <=0 | J41: 0
A42: 41 | B42: Restructured debt with regular payments for less than 6 months | C42: Rescheduled debt with regular payments for 6-12 months | D42: Overdue more than 90 days within the past 1 year | E42: (0, 50000000) | F42: >15 | G42: <=0 | H42: 99999999 | J42: 1
A43: 42 | B43: No debt restructuring history | C43: No debt rescheduling history (payment term relief) | D43: Record found in credit bureau but no delinquency history | E43: (50000000, 100000000) | F43: <=0 | G43: <=0 | H43: (0.5, 1) | I43: >2 | J43: 0
A44: 43 | B44: Restructured debt with regular payments for more than 12 months | C44: Rescheduled debt with regular payments for more than 12 months | D44: Record found in credit bureau but no delinquency history | E44: >250000000 | F44: >15 | G44: <=0 | H44: 99999998 | I44: (1.2, 2) | J44: 0
A45: 44 | B45: No debt restructuring history | C45: No debt rescheduling history (payment term relief) | D45: Record found in credit bureau but no delinquency history | E45: (50000000, 100000000) | F45: (0, 2.5) | G45: <=0 | H45: (0.5, 1) | I45: (0.75, 1) | J45: 0
A46: 45 | B46: No debt restructuring history | C46: Rescheduled debt with regular payments for more than 12 months | D46: Record found in credit bureau but no delinquency history | E46: (0, 50000000) | F46: <=0 | G46: <=0 | H46: 99999999 | I46: (0.5, 0.75) | J46: 0
A47: 46 | B47: No debt restructuring history | C47: Rescheduled debt with regular payments for more than 12 months | D47: Record found in credit bureau but no delinquency history | E47: (100000000, 150000000) | F47: (0, 2.5) | G47: <=0 | H47: <=0 | I47: (0.75, 1) | J47: 0
A48: 47 | B48: No debt restructuring history | C48: Rescheduled debt with regular payments for 6-12 months | D48: Overdue 61–90 days within the past 1 year | E48: >250000000 | F48: <=0 | G48: (15, 30) | H48: (1, 1.5) | I48: (0, 0.25) | J48: 0
A49: 48 | B49: Restructured debt with regular payments for 6-12 months | C49: Rescheduled debt with regular payments for 6-12 months | D49: Overdue more than 90 days within the past 1 year | E49: (50000000, 100000000) | F49: <=0 | G49: <=0 | H49: 99999998 | I49: <=0 | J49: 0
A50: 49 | B50: No debt restructuring history | C50: No debt rescheduling history (payment term relief) | D50: Record found in credit bureau but no delinquency history | E50: (0, 50000000) | F50: <=0 | G50: <=0 | H50: 99999998 | I50: <=0 | J50: 0
A51: 50 | B51: No debt restructuring history | C51: No debt rescheduling history (payment term relief) | D51: Credit bureau check not performed (exempted) | E51: >250000000 | F51: (7.5, 15) | G51: (0, 5) | H51: (0.5, 1) | I51: (0.75, 1) | J51: 0
A52: 51 | B52: No debt restructuring history | C52: No debt rescheduling history (payment term relief) | D52: Record found in credit bureau but no delinquency history | E52: (100000000, 150000000) | F52: (0, 2.5) | G52: <=0 | H52: (0, 0.5) | I52: (0.75, 1) | J52: 0
A53: 52 | B53: No debt restructuring history | C53: No debt rescheduling history (payment term relief) | D53: Record found in credit bureau but no delinquency history | E53: (0, 50000000) | F53: <=0 | G53: <=0 | H53: 99999999 | I53: <=0 | J53: 0
A54: 53 | B54: Restructured debt with regular payments for 6-12 months | C54: Rescheduled debt with regular payments for more than 12 months | D54: Overdue 1-30 days within the past 1 year | E54: (0, 50000000) | F54: <=0 | G54: <=0 | H54: (0.5, 1) | I54: >2 | J54: 0
A55: 54 | B55: No debt restructuring history | C55: No debt rescheduling history (payment term relief) | D55: Record found in credit bureau but no delinquency history | E55: >250000000 | F55: >15 | G55: (5, 15) | H55: 99999998 | I55: >2 | J55: 0
A56: 55 | B56: No debt restructuring history | C56: No debt rescheduling history (payment term relief) | D56: Record found in credit bureau but no delinquency history | E56: (0, 50000000) | F56: (2.5, 7.5) | G56: (0, 5) | H56: 99999998 | I56: (0.5, 0.75) | J56: 0
A57: 56 | B57: No debt restructuring history | C57: No debt rescheduling history (payment term relief) | D57: Record found in credit bureau but no delinquency history | E57: >250000000 | F57: <=0 | G57: <=0 | H57: (0.5, 1) | I57: (0, 0.25) | J57: 0
A58: 57 | B58: No debt restructuring history | C58: No debt rescheduling history (payment term relief) | D58: Record found in credit bureau but no delinquency history | E58: (50000000, 100000000) | F58: <=0 | G58: <=0 | H58: (1.5, 3) | I58: (0.25, 0.5) | J58: 0
A59: 58 | B59: No debt restructuring history | C59: No debt rescheduling history (payment term relief) | D59: Overdue 1-30 days within the past 1 year | E59: >250000000 | F59: (0, 2.5) | G59: (15, 30) | H59: (0.5, 1) | I59: (0.5, 0.75) | J59: 0
A60: 59 | B60: No debt restructuring history | C60: No debt rescheduling history (payment term relief) | D60: Record found in credit bureau but no delinquency history | E60: >250000000 | F60: <=0 | G60: <=0 | H60: (0, 0.5) | I60: (0, 0.25) | J60: 0
A61: 60 | B61: No debt restructuring history | C61: No debt rescheduling history (payment term relief) | D61: Record found in credit bureau but no delinquency history | E61: (150000000, 250000000) | F61: (2.5, 7.5) | G61: (0, 5) | H61: (0.5, 1) | I61: (0.75, 1) | J61: 0
A62: 61 | B62: No debt restructuring history | C62: No debt rescheduling history (payment term relief) | D62: Record found in credit bureau but no delinquency history | E62: (50000000, 100000000) | F62: (0, 2.5) | G62: (5, 15) | H62: >5 | I62: (1.2, 2) | J62: 0
A63: 62 | B63: No debt restructuring history | C63: No debt rescheduling history (payment term relief) | D63: Record found in credit bureau but no delinquency history | E63: >250000000 | F63: (7.5, 15) | G63: <=0 | H63: (3, 5) | I63: >2 | J63: 0
A64: 63 | B64: No debt restructuring history | C64: No debt rescheduling history (payment term relief) | D64: Record found in credit bureau but no delinquency history | E64: (0, 50000000) | F64: <=0 | G64: (0, 5) | H64: 99999998 | I64: (0, 0.25) | J64: 0
A65: 64 | B65: No debt restructuring history | C65: No debt rescheduling history (payment term relief) | D65: Record found in credit bureau but no delinquency history | E65: >250000000 | F65: (2.5, 7.5) | G65: (5, 15) | H65: (0, 0.5) | I65: >2 | J65: 0
A66: 65 | B66: No debt restructuring history | C66: No debt rescheduling history (payment term relief) | D66: Record found in credit bureau but no delinquency history | E66: >250000000 | F66: (2.5, 7.5) | G66: (5, 15) | H66: (0.5, 1) | I66: (1, 1.2) | J66: 0
A67: 66 | B67: No debt restructuring history | C67: No debt rescheduling history (payment term relief) | D67: Record found in credit bureau but no delinquency history | E67: (150000000, 250000000) | F67: <=0 | G67: <=0 | H67: (1, 1.5) | I67: <=0 | J67: 0
A68: 67 | B68: No debt restructuring history | C68: No debt rescheduling history (payment term relief) | D68: Record found in credit bureau but no delinquency history | E68: (150000000, 250000000) | F68: (0, 2.5) | G68: <=0 | H68: (1, 1.5) | I68: (1.2, 2) | J68: 0
A69: 68 | B69: No debt restructuring history | C69: No debt rescheduling history (payment term relief) | D69: Record found in credit bureau but no delinquency history | E69: (0, 50000000) | F69: <=0 | G69: (5, 15) | H69: 99999999 | I69: <=0 | J69: 0
A70: 69 | B70: No debt restructuring history | C70: Rescheduled debt with regular payments for less than 6 months | D70: Overdue 31–60 days more than 1 year ago | E70: (0, 50000000) | F70: <=0 | G70: <=0 | H70: 99999999 | I70: <=0 | J70: 0
A71: 70 | B71: No debt restructuring history | C71: No debt rescheduling history (payment term relief) | D71: Record found in credit bureau but no delinquency history | E71: (0, 50000000) | F71: <=0 | G71: <=0 | H71: 99999999 | I71: (0, 0.25) | J71: 0
A72: 71 | B72: No debt restructuring history | C72: No debt rescheduling history (payment term relief) | D72: Record found in credit bureau but no delinquency history | E72: (50000000, 100000000) | F72: <=0 | G72: <=0 | H72: 99999998 | I72: (0.25, 0.5) | J72: 0
A73: 72 | B73: No debt restructuring history | C73: No debt rescheduling history (payment term relief) | D73: Record found in credit bureau but no delinquency history | E73: >250000000 | F73: (7.5, 15) | G73: (0, 5) | H73: (0, 0.5) | I73: (1, 1.2) | J73: 0
A74: 73 | B74: No debt restructuring history | C74: No debt rescheduling history (payment term relief) | D74: Record found in credit bureau but no delinquency history | E74: (50000000, 100000000) | F74: >15 | G74: (15, 30) | H74: 99999998 | I74: >2 | J74: 0
A75: 74 | B75: No debt restructuring history | C75: No debt rescheduling history (payment term relief) | D75: Record found in credit bureau but no delinquency history | E75: (0, 50000000) | F75: <=0 | G75: >30 | H75: 99999998 | J75: 0
A76: 75 | B76: Restructured debt with regular payments for less than 6 months | C76: Rescheduled debt with regular payments for less than 6 months | D76: Overdue more than 90 days within the past 1 year | E76: >250000000 | F76: <=0 | G76: (5, 15) | H76: (1, 1.5) | I76: <=0 | J76: 0
A77: 76 | B77: No debt restructuring history | C77: No debt rescheduling history (payment term relief) | D77: Overdue 61–90 days within the past 1 year | E77: (100000000, 150000000) | F77: <=0 | G77: >30 | H77: 99999998 | I77: <=0 | J77: 1
A78: 77 | B78: No debt restructuring history | C78: No debt rescheduling history (payment term relief) | D78: Credit bureau check not performed (exempted) | E78: >250000000 | F78: (7.5, 15) | G78: (5, 15) | H78: (1, 1.5) | I78: >2 | J78: 0
A79: 78 | B79: No debt restructuring history | C79: No debt rescheduling history (payment term relief) | D79: Record found in credit bureau but no delinquency history | E79: (0, 50000000) | F79: <=0 | G79: <=0 | H79: (1.5, 3) | I79: <=0 | J79: 0
A80: 79 | B80: No debt restructuring history | C80: No debt rescheduling history (payment term relief) | D80: Record found in credit bureau but no delinquency history | E80: (50000000, 100000000) | F80: <=0 | G80: <=0 | H80: (0.5, 1) | I80: >2 | J80: 0
A81: 80 | B81: Restructured debt with regular payments for less than 6 months | C81: Rescheduled debt with regular payments for less than 6 months | D81: Overdue more than 90 days within the past 1 year | E81: >250000000 | F81: <=0 | G81: (5, 15) | H81: (1, 1.5) | I81: <=0 | J81: 0
A82: 81 | B82: No debt restructuring history | C82: Rescheduled debt with regular payments for more than 12 months | D82: Record found in credit bureau but no delinquency history | E82: (0, 50000000) | F82: (2.5, 7.5) | G82: (0, 5) | H82: 99999998 | I82: (0.75, 1) | J82: 0
A83: 82 | B83: No debt restructuring history | C83: Rescheduled debt with regular payments for less than 6 months | D83: Record found in credit bureau but no delinquency history | E83: (0, 50000000) | F83: <=0 | G83: <=0 | H83: 99999998 | I83: <=0 | J83: 0
A84: 83 | B84: No debt restructuring history | C84: No debt rescheduling history (payment term relief) | D84: No record found in credit bureau | J84: 0
A85: 84 | B85: No debt restructuring history | C85: No debt rescheduling history (payment term relief) | D85: Record found in credit bureau but no delinquency history | E85: >250000000 | F85: (2.5, 7.5) | G85: (5, 15) | H85: (0, 0.5) | I85: >2 | J85: 0
A86: 85 | B86: Restructured debt with regular payments for more than 12 months | C86: Rescheduled debt with regular payments for 6-12 months | D86: Credit bureau check not performed | E86: (0, 50000000) | F86: <=0 | G86: (0, 5) | H86: (1.5, 3) | I86: (0, 0.25) | J86: 1
A87: 86 | B87: Restructured debt with regular payments for 6-12 months | C87: Rescheduled debt with regular payments for 6-12 months | D87: Record found in credit bureau but no delinquency history | E87: (50000000, 100000000) | F87: <=0 | G87: <=0 | H87: 99999998 | I87: (0, 0.25) | J87: 1
A88: 87 | B88: No debt restructuring history | C88: No debt rescheduling history (payment term relief) | D88: Record found in credit bureau but no delinquency history | E88: (50000000, 100000000) | F88: (0, 2.5) | G88: <=0 | H88: (1, 1.5) | I88: (0.75, 1) | J88: 0
A89: 88 | B89: No debt restructuring history | C89: No debt rescheduling history (payment term relief) | D89: Record found in credit bureau but no delinquency history | E89: (0, 50000000) | F89: <=0 | G89: (5, 15) | H89: 99999998 | I89: (1.2, 2) | J89: 0
A90: 89 | B90: No debt restructuring history | C90: No debt rescheduling history (payment term relief) | D90: Record found in credit bureau but no delinquency history | E90: (150000000, 250000000) | F90: <=0 | G90: (5, 15) | H90: <=0 | I90: (0.75, 1) | J90: 0
A91: 90 | B91: Restructured debt with regular payments for 6-12 months | C91: Rescheduled debt with regular payments for more than 12 months | D91: Overdue 1-30 days within the past 1 year | E91: (50000000, 100000000) | F91: (0, 2.5) | G91: <=0 | H91: (1, 1.5) | I91: >2 | J91: 0
A92: 91 | B92: No debt restructuring history | C92: No debt rescheduling history (payment term relief) | D92: Record found in credit bureau but no delinquency history | E92: >250000000 | F92: >15 | G92: (5, 15) | H92: 99999998 | I92: >2 | J92: 0
A93: 92 | B93: No debt restructuring history | C93: No debt rescheduling history (payment term relief) | D93: Record found in credit bureau but no delinquency history | E93: >250000000 | F93: (2.5, 7.5) | G93: >30 | H93: (0, 0.5) | I93: (1.2, 2) | J93: 0
A94: 93 | B94: No debt restructuring history | C94: No debt rescheduling history (payment term relief) | D94: Credit bureau check not performed (exempted) | E94: >250000000 | F94: (7.5, 15) | G94: (0, 5) | H94: (0.5, 1) | I94: (0.75, 1) | J94: 0
A95: 94 | B95: Restructured debt with regular payments for less than 6 months | C95: Rescheduled debt with regular payments for 6-12 months | D95: Overdue 1-30 days within the past 1 year | E95: (0, 50000000) | F95: >15 | G95: >30 | H95: (0, 0.5) | J95: 1
A96: 95 | B96: Restructured debt with regular payments for 6-12 months | C96: Rescheduled debt with regular payments for 6-12 months | D96: Overdue 1-30 days within the past 1 year | E96: (50000000, 100000000) | F96: <=0 | G96: <=0 | H96: 99999998 | J96: 1
A97: 96 | B97: No debt restructuring history | C97: No debt rescheduling history (payment term relief) | D97: Record found in credit bureau but no delinquency history | E97: (0, 50000000) | F97: (2.5, 7.5) | G97: (0, 5) | H97: 99999998 | I97: (0.5, 0.75) | J97: 0
A98: 97 | B98: No debt restructuring history | C98: No debt rescheduling history (payment term relief) | D98: Record found in credit bureau but no delinquency history | E98: >250000000 | F98: (7.5, 15) | G98: (0, 5) | H98: (0, 0.5) | I98: (1, 1.2) | J98: 0
A99: 98 | B99: No debt restructuring history | C99: No debt rescheduling history (payment term relief) | D99: Record found in credit bureau but no delinquency history | E99: >250000000 | F99: <=0 | G99: (0, 5) | H99: 99999998 | I99: (0.25, 0.5) | J99: 0
A100: 99 | B100: No debt restructuring history | C100: No debt rescheduling history (payment term relief) | D100: Record found in credit bureau but no delinquency history | E100: >250000000 | F100: (2.5, 7.5) | G100: (5, 15) | H100: >5 | I100: >2 | J100: 0
...

Sheet Data_Bin_clean
A1: Cus_ID | B1: Debt restructuring history | C1: Debt rescheduling history (reschedule) | D1: Worst credit bureau delinquency record in the past 2 years | E1: Net Fixed Asset | F1: Net Profit Margin (%) | G1: Sale Growth (%) | H1: Debt-to-Equity Ratio | I1: Debt Service Coverage Area | J1: Default Flag
A2: 1 | B2: No debt restructuring history | C2: No debt rescheduling history (payment term relief) | D2: Record found in credit bureau but no delinquency history | E2: (0, 50000000) | F2: <=0 | G2: <=0 | H2: Not available | I2: <=0 | J2: 0
A3: 2 | B3: No debt restructuring history | C3: No debt rescheduling history (payment term relief) | D3: Record found in credit bureau but no delinquency history | E3: (0, 50000000) | F3: <=0 | G3: <=0 | H3: Not available | I3: <=0 | J3: 0
A4: 3 | B4: No debt restructuring history | C4: No debt rescheduling history (payment term relief) | D4: Record found in credit bureau but no delinquency history | E4: (150000000, 250000000) | F4: <=0 | G4: <=0 | H4: (0.5, 1) | I4: (0, 0.25) | J4: 0
A5: 4 | B5: No debt restructuring history | C5: No debt rescheduling history (payment term relief) | D5: Record found in credit bureau but no delinquency history | E5: >250000000 | F5: <=0 | G5: <=0 | H5: (0, 0.5) | I5: (0, 0.25) | J5: 0
A6: 5 | B6: Restructured debt with regular payments for more than 12 months | C6: Rescheduled debt with regular payments for more than 12 months | D6: Record found in credit bureau but no delinquency history | E6: >250000000 | F6: <=0 | G6: <=0 | H6: Not available | I6: (0.5, 0.75) | J6: 0
A7: 6 | B7: No debt restructuring history | C7: No debt rescheduling history (payment term relief) | D7: Record found in credit bureau but no delinquency history | E7: (50000000, 100000000) | F7: <=0 | G7: <=0 | H7: Not available | I7: <=0 | J7: 0
A8: 7 | B8: Restructured debt with regular payments for 6-12 months | C8: Rescheduled debt with regular payments for 6-12 months | D8: Overdue more than 90 days within the past 1 year | E8: >250000000 | F8: <=0 | G8: >30 | H8: (0.5, 1) | I8: <=0 | J8: 0
A9: 8 | B9: No debt restructuring history | C9: Rescheduled debt with regular payments for 6-12 months | D9: Record found in credit bureau but no delinquency history | E9: >250000000 | F9: (7.5, 15) | G9: >30 | H9: (1, 1.5) | I9: (0.75, 1) | J9: 0
A10: 9 | B10: No debt restructuring history | C10: Rescheduled debt with regular payments for more than 12 months | D10: Record found in credit bureau but no delinquency history | E10: (0, 50000000) | F10: <=0 | G10: <=0 | H10: Not available | I10: (0, 0.25) | J10: 0
A11: 10 | B11: No debt restructuring history | C11: No debt rescheduling history (payment term relief) | D11: Record found in credit bureau but no delinquency history | E11: (0, 50000000) | F11: <=0 | G11: <=0 | H11: (1, 1.5) | I11: <=0 | J11: 0
A12: 11 | B12: No debt restructuring history | C12: No debt rescheduling history (payment term relief) | D12: Record found in credit bureau but no delinquency history | E12: (0, 50000000) | F12: <=0 | G12: <=0 | H12: Not available | I12: <=0 | J12: 0
A13: 12 | B13: No debt restructuring history | C13: No debt rescheduling history (payment term relief) | D13: Record found in credit bureau but no delinquency history | E13: >250000000 | F13: (7.5, 15) | G13: <=0 | H13: (0, 0.5) | I13: (1.2, 2) | J13: 0
... A558: 557 | B558: No debt restructuring history | C558: Rescheduled debt with regular payments for more than 12 months | D558: Record found in credit bureau but no delinquency history | E558: (0, 50000000) | F558: (2.5, 7.5) | G558: <=0 | H558: Not available | I558: (0.25, 0.5) | J558: 0

Sheet Scorecard
A2: Unique key | B2: Index | C2: Feature | E2: Credit Score
A3: =CONCATENATE(C3,D3) -> Debt restructuring historyNever restructured debt | B3: C1 | C3: Debt restructuring history | D3: Never restructured debt | E3: 0
A4: =CONCATENATE(C4,D4) -> Debt restructuring historyNo debt restructuring history | C4: Debt restructuring history | D4: No debt restructuring history | E4: 0
A5: =CONCATENATE(C5,D5) -> Debt restructuring historyRestructured debt in the past | C5: Debt restructuring history | D5: Restructured debt in the past | E5: -50
A6: =CONCATENATE(C6,D6) -> Debt restructuring historyRestructured debt with regular payments for more than 12 months | C6: Debt restructuring history | D6: Restructured debt with regular payments for more than 12 months | E6: -50
A7: =CONCATENATE(C7,D7) -> Debt restructuring historyRestructured debt with regular payments for less than 6 months | C7: Debt restructuring history | D7: Restructured debt with regular payments for less than 6 months | E7: -100
A8: =CONCATENATE(C8,D8) -> Debt restructuring historyRestructured debt with regular payments for 6-12 months | C8: Debt restructuring history | D8: Restructured debt with regular payments for 6-12 months | E8: -100
A9: =CONCATENATE(C9,D9) -> Debt restructuring historyCredit bureau check not performed | C9: Debt restructuring history | D9: Credit bureau check not performed | E9: 0
A10: =CONCATENATE(C10,D10) -> Debt restructuring historyNot available | C10: Debt restructuring history | D10: Not available | E10: 0
A11: =CONCATENATE(C11,D11) -> Debt rescheduling history (reschedule)No debt rescheduling history (payment term relief) | B11: C2 | C11: Debt rescheduling history (reschedule) | D11: No debt rescheduling history (payment term relief) | E11: 0
A12: =CONCATENATE(C12,D12) -> Debt rescheduling history (reschedule)Rescheduled debt with regular payments for more than 12 months | C12: Debt rescheduling history (reschedule) | D12: Rescheduled debt with regular payments for more than 12 months | E12: -50
A13: =CONCATENATE(C13,D13) -> Debt rescheduling history (reschedule)Rescheduled debt with regular payments for less than 6 months | C13: Debt rescheduling history (reschedule) | D13: Rescheduled debt with regular payments for less than 6 months | E13: -100
A14: =CONCATENATE(C14,D14) -> Debt rescheduling history (reschedule)Rescheduled debt with regular payments for 6-12 months | C14: Debt rescheduling history (reschedule) | D14: Rescheduled debt with regular payments for 6-12 months | E14: -100
A15: =CONCATENATE(C15,D15) -> Debt rescheduling history (reschedule)Not available | C15: Debt rescheduling history (reschedule) | D15: Not available | E15: 0
A16: =CONCATENATE(C16,D16) -> Worst credit bureau delinquency record in the past 2 yearsRecord found in credit bureau but no delinquency history | B16: C3 | C16: Worst credit bureau delinquency record in the past 2 years | D16: Record found in credit bureau but no delinquency history | E16: 100
A17: =CONCATENATE(C17,D17) -> Worst credit bureau delinquency record in the past 2 yearsCredit bureau check not performed (exempted) | C17: Worst credit bureau delinquency record in the past 2 years | D17: Credit bureau check not performed (exempted) | E17: 100
A18: =CONCATENATE(C18,D18) -> Worst credit bureau delinquency record in the past 2 yearsNo record found in credit bureau | C18: Worst credit bureau delinquency record in the past 2 years | D18: No record found in credit bureau | E18: 0
A19: =CONCATENATE(C19,D19) -> Worst credit bureau delinquency record in the past 2 yearsOverdue 1–30 days more than 1 year ago | C19: Worst credit bureau delinquency record in the past 2 years | D19: Overdue 1–30 days more than 1 year ago | E19: -25
A20: =CONCATENATE(C20,D20) -> Worst credit bureau delinquency record in the past 2 yearsOverdue 1-30 days within the past 1 year | C20: Worst credit bureau delinquency record in the past 2 years | D20: Overdue 1-30 days within the past 1 year | E20: -25
A21: =CONCATENATE(C21,D21) -> Worst credit bureau delinquency record in the past 2 yearsOverdue 31–60 days more than 1 year ago | C21: Worst credit bureau delinquency record in the past 2 years | D21: Overdue 31–60 days more than 1 year ago | E21: -50
A22: =CONCATENATE(C22,D22) -> Worst credit bureau delinquency record in the past 2 yearsOverdue 31–60 days within the past 1 year | C22: Worst credit bureau delinquency record in the past 2 years | D22: Overdue 31–60 days within the past 1 year | E22: -50
A23: =CONCATENATE(C23,D23) -> Worst credit bureau delinquency record in the past 2 yearsOverdue 61–90 days more than 1 year ago | C23: Worst credit bureau delinquency record in the past 2 years | D23: Overdue 61–90 days more than 1 year ago | E23: -75
A24: =CONCATENATE(C24,D24) -> Worst credit bureau delinquency record in the past 2 yearsOverdue 61–90 days within the past 1 year | C24: Worst credit bureau delinquency record in the past 2 years | D24: Overdue 61–90 days within the past 1 year | E24: -75
A25: =CONCATENATE(C25,D25) -> Worst credit bureau delinquency record in the past 2 yearsOverdue more than 90 days more than 1 year ago | C25: Worst credit bureau delinquency record in the past 2 years | D25: Overdue more than 90 days more than 1 year ago | E25: -100
A26: =CONCATENATE(C26,D26) -> Worst credit bureau delinquency record in the past 2 yearsOverdue more than 90 days within the past 1 year | C26: Worst credit bureau delinquency record in the past 2 years | D26: Overdue more than 90 days within the past 1 year | E26: -100
A27: =CONCATENATE(C27,D27) -> Worst credit bureau delinquency record in the past 2 yearsCredit bureau check not performed | C27: Worst credit bureau delinquency record in the past 2 years | D27: Credit bureau check not performed | E27: -100
A28: =CONCATENATE(C28,D28) -> Worst credit bureau delinquency record in the past 2 yearsNot available | C28: Worst credit bureau delinquency record in the past 2 years | D28: Not available | E28: 0
A29: =CONCATENATE(C29,D29) -> Net Fixed Asset>250000000 | B29: F1 | C29: Net Fixed Asset | D29: >250000000 | E29: 100
A30: =CONCATENATE(C30,D30) -> Net Fixed Asset(150000000, 250000000) | C30: Net Fixed Asset | D30: (150000000, 250000000) | E30: 75
A31: =CONCATENATE(C31,D31) -> Net Fixed Asset(100000000, 150000000) | C31: Net Fixed Asset | D31: (100000000, 150000000) | E31: 50
A32: =CONCATENATE(C32,D32) -> Net Fixed Asset(50000000, 100000000) | C32: Net Fixed Asset | D32: (50000000, 100000000) | E32: 25
A33: =CONCATENATE(C33,D33) -> Net Fixed Asset(0, 50000000) | C33: Net Fixed Asset | D33: (0, 50000000) | E33: 0
A34: =CONCATENATE(C34,D34) -> Net Fixed AssetNot available | C34: Net Fixed Asset | D34: Not available | E34: 0
A35: =CONCATENATE(C35,D35) -> Net Profit Margin (%)>15 | B35: F2 | C35: Net Profit Margin (%) | D35: >15 | E35: 100
A36: =CONCATENATE(C36,D36) -> Net Profit Margin (%)(7.5, 15) | C36: Net Profit Margin (%) | D36: (7.5, 15) | E36: 75
A37: =CONCATENATE(C37,D37) -> Net Profit Margin (%)(2.5, 7.5) | C37: Net Profit Margin (%) | D37: (2.5, 7.5) | E37: 50
A38: =CONCATENATE(C38,D38) -> Net Profit Margin (%)(0, 2.5) | C38: Net Profit Margin (%) | D38: (0, 2.5) | E38: 25
A39: =CONCATENATE(C39,D39) -> Net Profit Margin (%)<=0 | C39: Net Profit Margin (%) | D39: <=0 | E39: -50
A40: =CONCATENATE(C40,D40) -> Net Profit Margin (%)Denominator equal to 0 (99999999) | C40: Net Profit Margin (%) | D40: Denominator equal to 0 (99999999) | E40: 0
A41: =CONCATENATE(C41,D41) -> Net Profit Margin (%)Not available | C41: Net Profit Margin (%) | D41: Not available | E41: 0
A42: =CONCATENATE(C42,D42) -> Sale Growth (%)>30 | B42: F3 | C42: Sale Growth (%) | D42: >30 | E42: 100
A43: =CONCATENATE(C43,D43) -> Sale Growth (%)(15, 30) | C43: Sale Growth (%) | D43: (15, 30) | E43: 75
A44: =CONCATENATE(C44,D44) -> Sale Growth (%)(5, 15) | C44: Sale Growth (%) | D44: (5, 15) | E44: 50
A45: =CONCATENATE(C45,D45) -> Sale Growth (%)(0, 5) | C45: Sale Growth (%) | D45: (0, 5) | E45: 25
A46: =CONCATENATE(C46,D46) -> Sale Growth (%)<=0 | C46: Sale Growth (%) | D46: <=0 | E46: 0
A47: =CONCATENATE(C47,D47) -> Sale Growth (%)Denominator equal to 0 (99999999) | C47: Sale Growth (%) | D47: Denominator equal to 0 (99999999) | E47: 0
A48: =CONCATENATE(C48,D48) -> Sale Growth (%)Not available | C48: Sale Growth (%) | D48: Not available | E48: 0
A49: =CONCATENATE(C49,D49) -> Debt-to-Equity Ratio(0, 0.5) | B49: F4 | C49: Debt-to-Equity Ratio | D49: (0, 0.5) | E49: 100
A50: =CONCATENATE(C50,D50) -> Debt-to-Equity Ratio(0.5, 1) | C50: Debt-to-Equity Ratio | D50: (0.5, 1) | E50: 80
A51: =CONCATENATE(C51,D51) -> Debt-to-Equity Ratio(1, 1.5) | C51: Debt-to-Equity Ratio | D51: (1, 1.5) | E51: 60
A52: =CONCATENATE(C52,D52) -> Debt-to-Equity Ratio(1.5, 3) | C52: Debt-to-Equity Ratio | D52: (1.5, 3) | E52: 40
A53: =CONCATENATE(C53,D53) -> Debt-to-Equity Ratio(3, 5) | C53: Debt-to-Equity Ratio | D53: (3, 5) | E53: 20
A54: =CONCATENATE(C54,D54) -> Debt-to-Equity Ratio>5 | C54: Debt-to-Equity Ratio | D54: >5 | E54: 0
A55: =CONCATENATE(C55,D55) -> Debt-to-Equity Ratio<=0 | C55: Debt-to-Equity Ratio | D55: <=0 | E55: 0
A56: =CONCATENATE(C56,D56) -> Debt-to-Equity RatioNegative Equity (99999998) | C56: Debt-to-Equity Ratio | D56: Negative Equity (99999998) | E56: 0
A57: =CONCATENATE(C57,D57) -> Debt-to-Equity RatioDenominator equal to 0 (99999999) | C57: Debt-to-Equity Ratio | D57: Denominator equal to 0 (99999999) | E57: 0
A58: =CONCATENATE(C58,D58) -> Debt-to-Equity RatioNot available | C58: Debt-to-Equity Ratio | D58: Not available | E58: 0
A59: =CONCATENATE(C59,D59) -> Debt Service Coverage Area>2 | B59: F5 | C59: Debt Service Coverage Area | D59: >2 | E59: 100
A60: =CONCATENATE(C60,D60) -> Debt Service Coverage Area(1.2, 2) | C60: Debt Service Coverage Area | D60: (1.2, 2) | E60: 90
A61: =CONCATENATE(C61,D61) -> Debt Service Coverage Area(1, 1.2) | C61: Debt Service Coverage Area | D61: (1, 1.2) | E61: 70
A62: =CONCATENATE(C62,D62) -> Debt Service Coverage Area(0.75, 1) | C62: Debt Service Coverage Area | D62: (0.75, 1) | E62: 50
A63: =CONCATENATE(C63,D63) -> Debt Service Coverage Area(0.5, 0.75) | C63: Debt Service Coverage Area | D63: (0.5, 0.75) | E63: 30
A64: =CONCATENATE(C64,D64) -> Debt Service Coverage Area(0.25, 0.5) | C64: Debt Service Coverage Area | D64: (0.25, 0.5) | E64: 10
A65: =CONCATENATE(C65,D65) -> Debt Service Coverage Area(0, 0.25) | C65: Debt Service Coverage Area | D65: (0, 0.25) | E65: 0
A66: =CONCATENATE(C66,D66) -> Debt Service Coverage Area<=0 | C66: Debt Service Coverage Area | D66: <=0 | E66: 0
A67: =CONCATENATE(C67,D67) -> Debt Service Coverage AreaNot available | C67: Debt Service Coverage Area | D67: Not available | E67: 0

Sheet Test
B3: Candidate Name:
B6: Please provide your answers below. The focus is to use data / quantitative analysis to justify / support your rationales / point of views.
B8: Current State
B9: The Bank's Credit Experts currently determine the weights of each feature and risk component of the scorecard based on expert judgement as follows:
B11: Risk Component / Feature | D11: Weight
B12: C_Credit History | D12: 0.5
C13: C1_History of Debt Restructuring | E13: 0.25
C14: C2_History of Debt Repayment with Rescheduling and Payment Relaxation | E14: 0.25
C15: C3_Worst Credit Bureau Delinquency Record in the Past 2 Years | E15: 0.5
B16: F_Financial Factor | D16: 0.5
C17: F1_Net Fixed Asset | E17: 0.2
C18: F2_Net Profit Margin (%) | E18: 0.2
C19: F3_Sale Growth (%) | E19: 0.2
C20: F4_Debt-to-Equity Ratio | E20: 0.2
C21: F5_Debt Service Coverage Ratio | E21: 0.2
B22: Note: Weights of C+F = 100%, C1+C2+C3 = 100%, F1+F2+F3+F4+F5 = 100%.
B24: Test Questions
B26: 1. Based on the information and data provided, please assess the assigned weights of each feature or risk component (Columns D & E). From the data and quantitative analysis perspective, which features or risk components are over- or under-weight? Please elaborate your rationales.
B27: Answers:
B31: 2. Any suggestions or enhancements regarding the formulated scorecard (i.e. to make it more sensible in terms of a good credit risk model)?
B32: Answers:
B36: 3. How would you approach EDA for a dataset containing borrower financial details, macroeconomic variables, and default history to identify key predictors of default?
B37: Answers:
B41: 4. Can you explain the steps involved in developing a logistic regression model to estimate the Probability of Default (PD) and describe the assumptions underlying this method?
B42: Answers:
B46: 5. How would you evaluate the performance of a logistic regression model for credit risk, including statistical goodness-of-fit, discriminatory power (e.g., AUC-ROC), and forecasting accuracy?
B47: Answers:
... B52: You are required to prepare up to a total of 12 slides covering the following areas, the presentation slides you draft will be used as part of the interview evaluation process.

Sheet Solution
B2: Question 1
C3: Methodology | D3: Implement Weight of Evidence method to measure the predictie power of independent variable in relation to target variable (default, non-default)
D4: The output is Information Value (IV) and it measures the different between event and non-event distribution
D5: Steps:
D6: (1) Assign each value to a bin. In case of continous variable, mapping its value to concrete bin.
D7: (2) Calculate WoE of each bin
D10: (3) Calculate IV Value by summing the WoE of every bin of that feature
D14: By convention, the meaning of IV values are:
D15: IV | E15: Predictive Power
D16: < 0.02 | E16: No predictive power
D17: 0.02 - 0.1 | E17: Weak
D18: 0.1 - 0.3 | E18: Moderate
D19: 0.3-0.5 | E19: Strong
D20: >= 0.5 | E20: Very strong
C22: Example | D22: Here is a IV detail calculation of Debt restructuring history
D24: No debt restructuring history | E24: Total | F24: Event | G24: Dist. Event | H24: Non Event | I24: Dist. Non Event | J24: WoE | K24: IV
D25: No debt restructuring history | E25: =COUNTIF(Data_Bin!$B:$B,D25) -> 233 | F25: =SUMIFS(Data_Bin!J:J,Data_Bin!B:B,D25) -> 12 | G25: =F25/SUM($F$25:$F$31) -> 0.24 | H25: =E25-F25 -> 221 | I25: =H25/SUM($H$25:$H$31) -> 0.43589744 | J25: =LN((G25+0.0000000001)/(I25+0.0000000001)) -> -0.59676805 | K25: =IFERROR(J25*(G25-I25),0) -> 0.11690533
D26: Restructured debt with regular payments for more than 12 months | E26: =COUNTIF(Data_Bin!$B:$B,D26) -> 16 | F26: =SUMIFS(Data_Bin!J:J,Data_Bin!B:B,D26) -> 4 | G26: =F26/SUM($F$25:$F$31) -> 0.08 | H26: =E26-F26 -> 12 | I26: =H26/SUM($H$25:$H$31) -> 0.023668639 | J26: =LN((G26+0.0000000001)/(I26+0.0000000001)) -> 1.2178757 | K26: =IFERROR(J26*(G26-I26),0) -> 0.068604596
D27: Restructured debt with regular payments for 6-12 months | E27: =COUNTIF(Data_Bin!$B:$B,D27) -> 18 | F27: =SUMIFS(Data_Bin!J:J,Data_Bin!B:B,D27) -> 8 | G27: =F27/SUM($F$25:$F$31) -> 0.16 | H27: =E27-F27 -> 10 | I27: =H27/SUM($H$25:$H$31) -> 0.019723866 | J27: =LN((G27+0.0000000001)/(I27+0.0000000001)) -> 2.0933444 | K27: =IFERROR(J27*(G27-I27),0) -> 0.29364627
D28: Restructured debt with regular payments for less than 6 months | E28: =COUNTIF(Data_Bin!$B:$B,D28) -> 8 | F28: =SUMIFS(Data_Bin!J:J,Data_Bin!B:B,D28) -> 5 | G28: =F28/SUM($F$25:$F$31) -> 0.1 | H28: =E28-F28 -> 3 | I28: =H28/SUM($H$25:$H$31) -> 0.0059171598 | J28: =LN((G28+0.0000000001)/(I28+0.0000000001)) -> 2.8273136 | K28: =IFERROR(J28*(G28-I28),0) -> 0.26600169
D29: Never restructured debt | E29: =COUNTIF(Data_Bin!$B:$B,D29) -> 271 | F29: =SUMIFS(Data_Bin!J:J,Data_Bin!B:B,D29) -> 21 | G29: =F29/SUM($F$25:$F$31) -> 0.42 | H29: =E29-F29 -> 250 | I29: =H29/SUM($H$25:$H$31) -> 0.49309665 | J29: =LN((G29+0.0000000001)/(I29+0.0000000001)) -> -0.16045048 | K29: =IFERROR(J29*(G29-I29),0) -> 0.011728392
D30: Restructured debt in the past | E30: =COUNTIF(Data_Bin!$B:$B,D30) -> 10 | F30: =SUMIFS(Data_Bin!J:J,Data_Bin!B:B,D30) -> 0 | G30: =F30/SUM($F$25:$F$31) -> 0 | H30: =E30-F30 -> 10 | I30: =H30/SUM($H$25:$H$31) -> 0.019723866 | J30: =LN((G30+0.0000000001)/(I30+0.0000000001)) -> -19.099925 | K30: =IFERROR(J30*(G30-I30),0) -> 0.37672436
D31: Credit bureau check not performed | E31: =COUNTIF(Data_Bin!$B:$B,D31) -> 1 | F31: =SUMIFS(Data_Bin!J:J,Data_Bin!B:B,D31) -> 0 | G31: =F31/SUM($F$25:$F$31) -> 0 | H31: =E31-F31 -> 1 | I31: =H31/SUM($H$25:$H$31) -> 0.0019723866 | J31: =LN((G31+0.0000000001)/(I31+0.0000000001)) -> -16.79734 | K31: =IFERROR(J31*(G31-I31),0) -> 0.033130848
D32: Sum | E32: =SUM(E25:E31) -> 557 | F32: =SUM(F25:F31) -> 50 | G32: =SUM(G25:G31) -> 1 | H32: =SUM(H25:H31) -> 507 | I32: =SUM(I25:I31) -> 1 | K32: =SUM(K25:K31) -> 1.1667415
D34: Similarly, a full IV index have been calculated using python (please refer working file)
C53: Suggestion | D53: C3_Worst credit bureau delinquency record in the past 2 years have been underweighted
D54: Bin 'Overdue more than 90 days more than 1 year ago' have 100% of default (7 samples) while 'Record found in credit bureau but no delinquency history' only have 5%
D55: Based on the IV calculation, this shoubd be the strongest predictor and the weight should be closer to 40%
D57: Similarly, F1_Net Fixed Asset is also a strong predictor. Smaller firms (NFA < 150 M) have higher rate of default (~12%) while bigger firms have lower rate of default (~2%)
D59: F3_Sale Growths(%) is massively overweighted. Default rates are flat across all bins (7-13%), no monotone relationship, hence this feature should be dropped or minimized.
D61: C2_Debt rescheduling history is also overweitght. It has less classifying power than C1, and nearly half of data is NA
B63: Question 2
C64: Approach 1 | D64: We will assess the rate of default in each bin of each feature to determine if the current linear method scoring in the scorecard is suitable
D65: Feature | E65: Debt rescheduling history (reschedule) | F65: Only select one option
D67: Bin | E67: Default Count. | F67: Total Count. | G67: Default Rate % | H67: Expert Scorecard score
D68: No debt rescheduling history (payment term relief) | E68: 9 | F68: 185 | G68: 4.86 | H68: 0
D69: Not available | E69: 21 | F69: 282 | G69: 7.45 | H69: 0
D70: Rescheduled debt with regular payments for 6-12 months | E70: 12 | F70: 27 | G70: 44.44 | H70: -100
D71: Rescheduled debt with regular payments for less than 6 months | E71: 4 | F71: 30 | G71: 13.33 | H71: -100
D72: Rescheduled debt with regular payments for more than 12 months | E72: 4 | F72: 33 | G72: 12.12 | H72: -50
D73: Grand Total | E73: 50 | F73: 557 | G73: 82.2 | H73: -250
D93: F3 Sale Growths
D94: Contrary to current scorecard grading, higher sales growth is associated with greater default risk.
D95: Firms with growth above 30% default at 11.4%, compared to 6.8–6.9% for firms with modest positive growth (0–15%)
D96: Suggesting that aggressive growth may signal financial distress rather than stability.
D97: My recommendation is to cap binning the score (grading firms with up to 15% rate with highest score)
D99: F2 Net Profit Margin %
D100: The >15% bin defaults at the same rate as loss-making firms, yet receives maximum score.
D101: The peak bin is moderate profitability (7.5–15%). Recommendation: cap max score at (7.5, 15) bin; reduce score for >15%.
D103: F4 Debt to Equity Ratio
D104: The firms in (0, 0.5) bin have 20% of defaults, much higher than those in (0.5-1.5) bin
D105: This may be indicator of not well leverage cash flow.
D106: My recommendation is to shift max score to (0.5, 1) and restructure bin score around this empirical spot
... D112: Recommendation: change scores of these 3 pins to ensure consistent treatment
C114: Approach 2 | D114: Implement a logistic regression model on the dataset to determine the score of each bin of each feature
D115: Steps:
D116: (1) Cleaning data, replace NA with Not Available, merge 9999999 and 9999998 to one bin
D117: (2) Calculate WoE of each bin
D118: (3) Replace WoE value to each bin
D119: (4) Fit to a linear regression model
D120: (5) Test and validate result on test data
D121: (6) Use the rate of default to calculate the scoring of each bin
D123: The methodology of step 4 and 5 will be presented in next parts
D124: In step 6, we scaling the PD to scoring for interpretable and linear scale
D125: Convert PD to Log-Odds, this map (0, 1) to (-inf, inf)
D129: Scale the score
D131: We adopt the convention parameters of Base Score = 600, PDO = 20, Base Odds = 50:1
... D135: Please refer to ipynb file for detail calculation
B137: Question 3 | D137: To determine the key predictor of defaults in a dataset, we must closely inspect the relations of each variable with the default history in order to determine the causal relationship of that variable to default probability.
D138: Macroeconomic variables usually effect the whole market, and its effect need to be studied in at least a business cycle
D139: We should perform correlation analysis on the macroeconomic variables against the aggregated portfolio default rate overtime (as a whole market or separate by sector)
D140: It is also noted that macro effects on default are lagged, hence it is necessary to test for multiple lag period
D141: Financial details offer predictive power on the firm-level
D142: The dataset provided only have financial details, and I suggest the following step to EDA this data
D143: I have performed this procedure, please refer to ipynb file for details
D145: (1) Data understanding and quality check
D146: Begin by profiling the dataset to establish a baseline understanding of its structure and integrity.
D147: This includes examining variable types (categorical vs. numerical), sample size, and class distribution of the target variable.
D148: Key checks include:
D149: Missing values: distinguish true nulls from sentinel values (e.g. 99999998, 99999999 indicating invalid calculations or negative equity)
D150: Distribution & skewness: identify heavily skewed features that may require log transformation or capping
... D166: Calculate Weight of Evidence (WoE) and Information Value (IV) for each feature to quantitatively determine discriminatory power against the default target
B168: Question 4 | D168: A logistic model (or logit model) is a statistical model that models the log-odds of an event as a linear combination of one or more independent variables.
D169: In regression analysis, logistic regression estimates the parameters of a logistic model
D170: A binary logistic regression can be used to model Probability of Default (PD), with output of 0 and 1
C171: Methodology | D171: General formula of Linear Regression
D175: - Continuous, real-valued, and bounded within (0, 1)
D176: - Points far to the right approach 1, points far to the left approach 0
D177: - Smooth (differentiable everywhere) to enable optimization
D178: The most commonly used logistic function is the sigmoid
D180: Loss Function and Optimization
D181: Given a data point xᵢ with label yᵢ (0 or 1), the model estimates
D182: P(yᵢ = 1 | xᵢ; w) = f(wᵀxᵢ) = zᵢ
D183: P(yᵢ = 0 | xᵢ; w) = 1 − zᵢ
D184: These two expressions can be combined into one:
D187: The goal is to find w that maximizes the likelihood of observing the training data. This is called Maximum Likelihood Estimation (MLE)
D188: Assuming data points are independently:
D192: To avoid numerical issues (product of many small numbers) and simplify optimization, we take the negative log-likelihood as the loss function:
... D204: Rule of thump is predict class 1 if this probability greater than 0.5
C205: Assumption | D205: Binary or Ordinal Dependent Variable
...

Sheet Default Rate By bin
A1: Feature | B1: Bin | C1: Default Count | D1: Total Count | E1: Default Rate | F1: Scorecard score
A2: Debt restructuring history | B2: No debt restructuring history | C2: {=SUMPRODUCT((INDEX(Data_Bin_clean!$B$2:$J$558,0,MATCH(A2,Data_Bin_clean!$B$1:$J$1,0))=B2)*(Data_Bin_clean!$J$2:$J$558=1))} -> 12 | D2: {=SUMPRODUCT((INDEX(Data_Bin_clean!$B$2:$J$558,0,MATCH(A2,Data_Bin_clean!$B$1:$J$1,0))=B2)*1)} -> 233 | E2: =IFERROR(ROUND(C2/D2*100,2),0) -> 5.15 | F2: {=_xlfn.XLOOKUP(A2&"|"&B2,Scorecard!$C$2:$C$67&"|"&Scorecard!$D$2:$D$67,Scorecard!$E$2:$E$67,0)} -> 0
A3: Debt restructuring history | B3: Restructured debt with regular payments for more than 12 months | C3: {=SUMPRODUCT((INDEX(Data_Bin_clean!$B$2:$J$558,0,MATCH(A3,Data_Bin_clean!$B$1:$J$1,0))=B3)*(Data_Bin_clean!$J$2:$J$558=1))} -> 4 | D3: {=SUMPRODUCT((INDEX(Data_Bin_clean!$B$2:$J$558,0,MATCH(A3,Data_Bin_clean!$B$1:$J$1,0))=B3)*1)} -> 16 | E3: =IFERROR(ROUND(C3/D3*100,2),0) -> 25 | F3: {=_xlfn.XLOOKUP(A3&"|"&B3,Scorecard!$C$2:$C$67&"|"&Scorecard!$D$2:$D$67,Scorecard!$E$2:$E$67,0)} -> -50
A4: Debt restructuring history | B4: Restructured debt with regular payments for 6-12 months | C4: {=SUMPRODUCT((INDEX(Data_Bin_clean!$B$2:$J$558,0,MATCH(A4,Data_Bin_clean!$B$1:$J$1,0))=B4)*(Data_Bin_clean!$J$2:$J$558=1))} -> 8 | D4: {=SUMPRODUCT((INDEX(Data_Bin_clean!$B$2:$J$558,0,MATCH(A4,Data_Bin_clean!$B$1:$J$1,0))=B4)*1)} -> 18 | E4: =IFERROR(ROUND(C4/D4*100,2),0) -> 44.44 | F4: {=_xlfn.XLOOKUP(A4&"|"&B4,Scorecard!$C$2:$C$67&"|"&Scorecard!$D$2:$D$67,Scorecard!$E$2:$E$67,0)} -> -100
A5: Debt restructuring history | B5: Restructured debt with regular payments for less than 6 months | C5: {=SUMPRODUCT((INDEX(Data_Bin_clean!$B$2:$J$558,0,MATCH(A5,Data_Bin_clean!$B$1:$J$1,0))=B5)*(Data_Bin_clean!$J$2:$J$558=1))} -> 5 | D5: {=SUMPRODUCT((INDEX(Data_Bin_clean!$B$2:$J$558,0,MATCH(A5,Data_Bin_clean!$B$1:$J$1,0))=B5)*1)} -> 8 | E5: =IFERROR(ROUND(C5/D5*100,2),0) -> 62.5 | F5: {=_xlfn.XLOOKUP(A5&"|"&B5,Scorecard!$C$2:$C$67&"|"&Scorecard!$D$2:$D$67,Scorecard!$E$2:$E$67,0)} -> -100
A6: Debt restructuring history | B6: Never restructured debt | C6: {=SUMPRODUCT((INDEX(Data_Bin_clean!$B$2:$J$558,0,MATCH(A6,Data_Bin_clean!$B$1:$J$1,0))=B6)*(Data_Bin_clean!$J$2:$J$558=1))} -> 21 | D6: {=SUMPRODUCT((INDEX(Data_Bin_clean!$B$2:$J$558,0,MATCH(A6,Data_Bin_clean!$B$1:$J$1,0))=B6)*1)} -> 271 | E6: =IFERROR(ROUND(C6/D6*100,2),0) -> 7.75 | F6: {=_xlfn.XLOOKUP(A6&"|"&B6,Scorecard!$C$2:$C$67&"|"&Scorecard!$D$2:$D$67,Scorecard!$E$2:$E$67,0)} -> 0
A7: Debt restructuring history | B7: Restructured debt in the past | C7: {=SUMPRODUCT((INDEX(Data_Bin_clean!$B$2:$J$558,0,MATCH(A7,Data_Bin_clean!$B$1:$J$1,0))=B7)*(Data_Bin_clean!$J$2:$J$558=1))} -> 0 | D7: {=SUMPRODUCT((INDEX(Data_Bin_clean!$B$2:$J$558,0,MATCH(A7,Data_Bin_clean!$B$1:$J$1,0))=B7)*1)} -> 10 | E7: =IFERROR(ROUND(C7/D7*100,2),0) -> 0 | F7: {=_xlfn.XLOOKUP(A7&"|"&B7,Scorecard!$C$2:$C$67&"|"&Scorecard!$D$2:$D$67,Scorecard!$E$2:$E$67,0)} -> -50
A8: Debt restructuring history | B8: Credit bureau check not performed | C8: {=SUMPRODUCT((INDEX(Data_Bin_clean!$B$2:$J$558,0,MATCH(A8,Data_Bin_clean!$B$1:$J$1,0))=B8)*(Data_Bin_clean!$J$2:$J$558=1))} -> 0 | D8: {=SUMPRODUCT((INDEX(Data_Bin_clean!$B$2:$J$558,0,MATCH(A8,Data_Bin_clean!$B$1:$J$1,0))=B8)*1)} -> 1 | E8: =IFERROR(ROUND(C8/D8*100,2),0) -> 0 | F8: {=_xlfn.XLOOKUP(A8&"|"&B8,Scorecard!$C$2:$C$67&"|"&Scorecard!$D$2:$D$67,Scorecard!$E$2:$E$67,0)} -> 0
A9: Debt restructuring history | B9: Not available | C9: {=SUMPRODUCT((INDEX(Data_Bin_clean!$B$2:$J$558,0,MATCH(A9,Data_Bin_clean!$B$1:$J$1,0))=B9)*(Data_Bin_clean!$J$2:$J$558=1))} -> 0 | D9: {=SUMPRODUCT((INDEX(Data_Bin_clean!$B$2:$J$558,0,MATCH(A9,Data_Bin_clean!$B$1:$J$1,0))=B9)*1)} -> 0 | E9: =IFERROR(ROUND(C9/D9*100,2),0) -> 0 | F9: {=_xlfn.XLOOKUP(A9&"|"&B9,Scorecard!$C$2:$C$67&"|"&Scorecard!$D$2:$D$67,Scorecard!$E$2:$E$67,0)} -> 0
A10: Debt rescheduling history (reschedule) | B10: No debt rescheduling history (payment term relief) | C10: {=SUMPRODUCT((INDEX(Data_Bin_clean!$B$2:$J$558,0,MATCH(A10,Data_Bin_clean!$B$1:$J$1,0))=B10)*(Data_Bin_clean!$J$2:$J$558=1))} -> 9 | D10: {=SUMPRODUCT((INDEX(Data_Bin_clean!$B$2:$J$558,0,MATCH(A10,Data_Bin_clean!$B$1:$J$1,0))=B10)*1)} -> 185 | E10: =IFERROR(ROUND(C10/D10*100,2),0) -> 4.86 | F10: {=_xlfn.XLOOKUP(A10&"|"&B10,Scorecard!$C$2:$C$67&"|"&Scorecard!$D$2:$D$67,Scorecard!$E$2:$E$67,0)} -> 0
A11: Debt rescheduling history (reschedule) | B11: Rescheduled debt with regular payments for more than 12 months | C11: {=SUMPRODUCT((INDEX(Data_Bin_clean!$B$2:$J$558,0,MATCH(A11,Data_Bin_clean!$B$1:$J$1,0))=B11)*(Data_Bin_clean!$J$2:$J$558=1))} -> 4 | D11: {=SUMPRODUCT((INDEX(Data_Bin_clean!$B$2:$J$558,0,MATCH(A11,Data_Bin_clean!$B$1:$J$1,0))=B11)*1)} -> 33 | E11: =IFERROR(ROUND(C11/D11*100,2),0) -> 12.12 | F11: {=_xlfn.XLOOKUP(A11&"|"&B11,Scorecard!$C$2:$C$67&"|"&Scorecard!$D$2:$D$67,Scorecard!$E$2:$E$67,0)} -> -50
A12: Debt rescheduling history (reschedule) | B12: Rescheduled debt with regular payments for 6-12 months | C12: {=SUMPRODUCT((INDEX(Data_Bin_clean!$B$2:$J$558,0,MATCH(A12,Data_Bin_clean!$B$1:$J$1,0))=B12)*(Data_Bin_clean!$J$2:$J$558=1))} -> 12 | D12: {=SUMPRODUCT((INDEX(Data_Bin_clean!$B$2:$J$558,0,MATCH(A12,Data_Bin_clean!$B$1:$J$1,0))=B12)*1)} -> 27 | E12: =IFERROR(ROUND(C12/D12*100,2),0) -> 44.44 | F12: {=_xlfn.XLOOKUP(A12&"|"&B12,Scorecard!$C$2:$C$67&"|"&Scorecard!$D$2:$D$67,Scorecard!$E$2:$E$67,0)} -> -100
A13: Debt rescheduling history (reschedule) | B13: Rescheduled debt with regular payments for less than 6 months | C13: {=SUMPRODUCT((INDEX(Data_Bin_clean!$B$2:$J$558,0,MATCH(A13,Data_Bin_clean!$B$1:$J$1,0))=B13)*(Data_Bin_clean!$J$2:$J$558=1))} -> 4 | D13: {=SUMPRODUCT((INDEX(Data_Bin_clean!$B$2:$J$558,0,MATCH(A13,Data_Bin_clean!$B$1:$J$1,0))=B13)*1)} -> 30 | E13: =IFERROR(ROUND(C13/D13*100,2),0) -> 13.33 | F13: {=_xlfn.XLOOKUP(A13&"|"&B13,Scorecard!$C$2:$C$67&"|"&Scorecard!$D$2:$D$67,Scorecard!$E$2:$E$67,0)} -> -100
... A60: Debt Service Coverage Area | B60: Not available | C60: {=SUMPRODUCT((INDEX(Data_Bin_clean!$B$2:$J$558,0,MATCH(A60,Data_Bin_clean!$B$1:$J$1,0))=B60)*(Data_Bin_clean!$J$2:$J$558=1))} -> 18 | D60: {=SUMPRODUCT((INDEX(Data_Bin_clean!$B$2:$J$558,0,MATCH(A60,Data_Bin_clean!$B$1:$J$1,0))=B60)*1)} -> 122 | E60: =IFERROR(ROUND(C60/D60*100,2),0) -> 14.75 | F60: {=_xlfn.XLOOKUP(A60&"|"&B60,Scorecard!$C$2:$C$67&"|"&Scorecard!$D$2:$D$67,Scorecard!$E$2:$E$67,0)} -> 0
A61: Debt Service Coverage Area | B61: >2 | C61: 3 | D61: {=SUMPRODUCT((INDEX(Data_Bin_clean!$B$2:$J$558,0,MATCH(A61,Data_Bin_clean!$B$1:$J$1,0))=B61)*1)} -> 41 | E61: =IFERROR(ROUND(C61/D61*100,2),0) -> 7.32 | F61: {=_xlfn.XLOOKUP(A61&"|"&B61,Scorecard!$C$2:$C$67&"|"&Scorecard!$D$2:$D$67,Scorecard!$E$2:$E$67,0)} -> 100
A62: Debt Service Coverage Area | B62: (1, 1.2) | C62: 3 | D62: {=SUMPRODUCT((INDEX(Data_Bin_clean!$B$2:$J$558,0,MATCH(A62,Data_Bin_clean!$B$1:$J$1,0))=B62)*1)} -> 28 | E62: =IFERROR(ROUND(C62/D62*100,2),0) -> 10.71 | F62: {=_xlfn.XLOOKUP(A62&"|"&B62,Scorecard!$C$2:$C$67&"|"&Scorecard!$D$2:$D$67,Scorecard!$E$2:$E$67,0)} -> 70
